Workbook

Sheet Leia-me
A1: Planilha de triagem – Síndrome de Edwards (T18): sobrevida e desfecho gestacional
A3: Buscas: data, horário e número de registros
A4: Busca A – registros recuperados para a triagem: 29/09/2026, 19h21 (horário de Brasília; 22h21 UTC) – 253 registros
A5: Busca B – registros recuperados para a triagem: 29/09/2026, 19h21 (horário de Brasília; 22h21 UTC) – 241 registros
A6: Buscas A e B – reexecução de conferência: 29/09/2026, 19h48 (horário de Brasília; 22h48 UTC) – 253 e 241 registros; mesmos 449 registros distintos
A7: Busca A – execução pelo pesquisador na interface do PubMed: 29/09/2026, 19h20 (horário de Brasília; 22h21 UTC) – 253 registros
A8: Busca B – execução pelo pesquisador na interface do PubMed: 29/09/2026, 19h47 (horário de Brasília; 22h48 UTC) – 241 registros
A9: Base: PubMed. Os horários de 19h21 e 19h48 correspondem à recuperação dos registros pela interface de programação do PubMed (E-utilities) e foram registrados pelo sistema de arquivos do ambiente de trabalho. Um minuto antes de cada uma delas, o pesquisador rodou as buscas na interface do site.
A11: Desenho da revisão: três revisores de IA independentes e arbitragem humana
A12: Revisor 1 – Claude (Anthropic): triagem inicial de título e resumo, registrada na aba Triagem.
A13: Revisor 2 – Gemini (Google): revisão independente, registrada na aba Revisão_Gemini.
A14: Revisor 3 – ChatGPT (OpenAI): revisão independente, registrada na aba Revisão_ChatGPT.
... A80: 4. Abas de revisão: a versão do modelo aparece como "3.0" (Gemini) e "1.0" (ChatGPT). Registrar o nome completo do modelo (por exemplo, o que a própria interface informa), para que a revisão seja reproduzível.

Sheet Prompt_revisores
A1: Texto padronizado para o Gemini e o ChatGPT (copiar e colar sem alterações, seguido do lote de registros)
A3: Você é um revisor independente de uma triagem de literatura científica (etapa de título e resumo) para um artigo jurídico sobre a síndrome de Edwards (trissomia 18, T18).
A4: PERGUNTA A: estudos com dados de sobrevida ou mortalidade de nascidos vivos com T18.
A5: PERGUNTA B: estudos com dados sobre o desfecho de gestações após diagnóstico pré-natal de T18 (nascido vivo, perda espontânea, óbito fetal, natimorto).
A6: INCLUIR: dados originais de sobrevida/mortalidade (A) ou de desfecho gestacional (B), específicos para T18 ou separáveis de outras condições; ou revisões sistemáticas desses estudos. Séries de casos são aceitas; relatos de caso isolados não.
A7: APOIO: textos sem dados de desfecho, mas úteis ao debate (diretrizes, consensos, ética, terminologia, qualidade de vida, contrapontos).
A8: EXCLUIR, com um código: E1 fora do tema (não trata da síndrome como objeto); E2 rastreamento/diagnóstico pré-natal sem desfecho específico da T18; E3 outra anomalia como objeto, T18 só como achado associado; E4 sem dados próprios e sem utilidade direta; E5 sem desfecho de sobrevida ou gestacional; E6 relato de caso ou capítulo; E7 T18 não é objeto ou dados não separáveis; E8 prevalência/epidemiologia sem desfecho; E9 apenas trissomia parcial ou mosaico.
A9: REGRAS: (1) decida SOMENTE com base no título e no resumo fornecidos; não use conhecimento externo sobre o artigo e não pesquise na internet; (2) não invente informações que não estejam no resumo; (3) se a informação for insuficiente para decidir, escolha Incluir e escreva 'informação insuficiente – verificar texto completo'; (4) avalie todas as linhas do lote, sem omitir nenhuma.
A10: FORMATO DA RESPOSTA: uma tabela com as colunas PMID | Decisão (Incluir, Excluir ou Apoio) | Pergunta (A, B ou A+B, só se Incluir) | Código (E1 a E9, só se Excluir) | Justificativa (uma frase citando o elemento do título ou do resumo que fundamenta a decisão). Mantenha a mesma ordem das linhas recebidas.

Sheet Triagem
A1: PMID | B1: Ano | C1: Primeiro autor | D1: Título | E1: Resumo | F1: Periódico | G1: Tipo de publicação | H1: Busca | I1: Decisão – Claude | J1: Pergunta – Claude | K1: Código – Claude | L1: Motivo / descrição | M1: Nota | N1: Link PubMed | O1: Ano ≥ 2024
A2: 40831321 | B2: 2026 | C2: Nemoto S | D2: Current Nationwide Landscape of Cardiac Surgery for Children With Trisomy 18 in Japan. | E2: Despite the increasing number of retrospective cohorts describing successful cardiac surgery for children with trisomy 18, no consensus has been reached among healthcare providers regarding cardiac surgery in Japan. This study provided a benchmark to facilitate consensus building by assessing a nationwide surgical database in Japan. A total of 78,179 cardiothoracic surgeries performed for children with congenital heart disease were registered in the Japan Cardiovascular Surgery Database Congenital Section from 2013 to 2021. Of these, 789 (1.0%) surgeries were performed for 502 children with trisomy 18 with increasing yearly trends. Of these, 490 cases (96.1%) of mild-to-moderate cardiac lesions underwent simple surgery, whereas 600 closed-heart surgeries accounted for 76.0%. Approximately 19.4% of the cases were associated with noncardiac lesions that led to postoperative complications at a frequency of 35.3%, whereas cardiac-related postoperative complications accounted for 30.5%. Severe infections occurred postoperatively in approximately 9% of the cases. Forty-two (8.4%) patients died in-hospital, of which the most common cause was heart-related, followed by respiratory-related and infection. This nationwide database analysis may provide valuable information that may serve as a benchmark and enable us to better define the patient attributes that will maximize the effectiveness of cardiac surgery for the vulnerable children. | F2: Am J Med Genet A | G2: Journal Article | H2: A | I2: Incluir | J2: A | N2: =HYPERLINK("https://pubmed.ncbi.nlm.nih.gov/40831321/","abrir") -> abrir | O2: =IF(B2 < 2024, FALSE() , TRUE()) -> TRUE
A3: 41485045 | B3: 2026 | C3: Caggiano S | D3: Survival in infants with trisomy 18, palliative care and ethical reflections: a single center considerations. | E3: BACKGROUND: Trisomy 18 was once considered a fatal diagnosis due to the presence of cardiac and extracardiac lesions. However, with the increasing use of therapeutic management, 3% to 25% of infants with trisomy 18 may survive beyond their first year, depending on the interventions provided. Currently, there are no clear and widely accepted criteria to guide medical decisions for children with trisomy 18. This means that patients could often be at risk of either over-treatment or therapeutic abandonment. We aimed to explore the effectiveness of intensive and non-intensive treatments in enhancing the clinical burden of disease and survival of children with trisomy 18 syndrome METHODS: a retrospective monocentric study in Bambino Gesù Children’s Hospital, IRCCS Rome, Italy. We enrolled all patients discharged from our hospital with genetic diagnosis of trisomy 18 between 2018 and 2023. Clinical data from birth were collected and categorized into two groups: those who received intensive treatment and those who underwent a palliative approach. Intensive treatment was defined as corrective heart surgery, use of invasive respiratory support, or at least one hospitalization in an intensive care unit. Survival probabilities at different age intervals were calculated, and the clinical burden of disease was assessed, taking into account device dependence, number of emergency department visits per year, and the daily intake of medications at home RESULTS: 32 patients were enrolled. Children with a low device dependence had significantly higher survival(p= 0,01). Neither palliative nor corrective heart surgery affected survival for patients with major cardiac defects. Conversely in children with minor heart defects surgery significantly increased survival probability(p= 0.01), particularly the corrective approach(p= 0.01). High number of emergency department visits(p=0.03) and high number of drugs taken daily(p=0.02) significantly reduced survival. No significant differences emerged between the two groups in terms of burden of disease. CONCLUSIONS: proportional to the initial clinical conditions all treatment options, which may include both comfort care and heart surgery, should be re-evaluated to determine the approach that prioritizes the best interest of each child with trisomy 18. | F3: Ital J Pediatr | G3: Journal Article | H3: A | I3: Incluir | J3: A | N3: =HYPERLINK("https://pubmed.ncbi.nlm.nih.gov/41485045/","abrir") -> abrir | O3: =IF(B3 < 2024, FALSE() , TRUE()) -> TRUE
A4: 41749627 | B4: 2026 | C4: Uygur Külcü N | D4: Trisomy 18 and Trisomy 13: A Retrospective Cohort Study at a Tertiary Hospital. | E4: BACKGROUND: Trisomy 18 (T18; Edwards syndrome) and Trisomy 13 (T13; Patau syndrome) are rare autosomal aneuploidies characterized by severe congenital anomalies, high neonatal mortality, and complex clinical trajectories. OBJECTIVE: This study aimed to describe the clinical features, management approaches, and outcomes of genetically confirmed patients aged 0-18 years diagnosed with T18 or T13 in a tertiary care center. METHODS: This retrospective study reviewed hospital records of genetically confirmed T18 and T13 cases identified through ICD-10 codes (Q91-Q92) between January 2015 and December 2024. Patients aged 0-18 years at diagnosis were included. Demographic, clinical, and interventional data were collected from electronic medical records. Survival analyses were conducted using the Kaplan-Meier method, with comparisons assessed using the log-rank test. RESULTS: Among 29 patients, 23 had T18 and 6 had T13. Cardiovascular involvement was the most frequent anomaly, and overall mortality was high despite intensive care. Median survival was 90 days for T18 and 120 days for T13, with more than 80% surviving the first month but showing a steep decline thereafter. Most deaths were attributed to cardiopulmonary complications or sepsis secondary to prolonged intensive care. Kaplan-Meier analysis revealed marked early mortality in both groups, with no significant survival difference (log-rank p ≈ 0.3). A small subset demonstrated longer-term survival with heterogeneous clinical courses. CONCLUSIONS: T18 and T13 are associated with high early mortality driven by complex congenital heart disease, respiratory instability, and infection-related complications. Although the overall prognosis remains poor, a minority of patients achieve extended survival, highlighting variable trajectories. Early multidisciplinary care, individualized decision-making, and strict infection prevention remain essential to optimize outcomes and support families. | F4: Children (Basel) | G4: Journal Article | H4: A | I4: Incluir | J4: A | N4: =HYPERLINK("https://pubmed.ncbi.nlm.nih.gov/41749627/","abrir") -> abrir | O4: =IF(B4 < 2024, FALSE() , TRUE()) -> TRUE
A5: 41840151 | B5: 2026 | C5: Sugai S | D5: Annual trends and regional variations in medical interventions and survival to discharge for trisomies 18 and 13, 2011-2022: a nationwide inpatient database study. | E5: OBJECTIVE: This study examines annual trends and regional disparities in interventions and in-hospital outcomes for trisomies 18 and 13. STUDY DESIGN: We conducted a retrospective cohort study using nationwide data from 2011 to 2022. Patients with trisomies 18 and 13 admitted on the day of birth were identified. Nonsurgical and surgical intervention rates, survival to discharge, length of stay, and costs were analyzed by year and region. RESULT: This study identified 2 245 neonates with trisomy 18 (n = 1 808) and trisomy 13 (n = 437). Nonsurgical and surgical intervention rates increased annually. Between 2011 and 2022, survival to discharge rates improved from 44.5 to 57.9%, and both hospital length of stay and costs nearly doubled. Regional disparities in survival to discharge rates were significant, with differences of up to 21.5%. CONCLUSION: We observed an increase in interventions and a corresponding improvement in survival to discharge, with significant regional variations. | F5: J Perinatol | G5: Journal Article | H5: A | I5: Incluir | J5: A | M5: Coorte nacional japonesa 2011–2022 (1.808 T18). | N5: =HYPERLINK("https://pubmed.ncbi.nlm.nih.gov/41840151/","abrir") -> abrir | O5: =IF(B5 < 2024, FALSE() , TRUE()) -> TRUE
A6: 42302673 | B6: 2026 | C6: Lee T | D6: Characteristics and Outcomes of Pediatric Trisomy 13 and 18 Inpatient Admissions in Texas. | E6: INTRODUCTION: Trisomy 13 (T13, Patau syndrome) and trisomy 18 (T18, Edwards syndrome) are the second and third most common aneuploidies with significant morbidity and mortality. Survival beyond infancy is becoming increasingly recognized. However, surgical needs of these populations are not well described. We aim to investigate the characteristics and outcomes of the surgical care of pediatric patients with T13 and T18 in Texas. METHODS: The Texas Hospital Inpatient Discharge Public Use Data File (2017-2023) was queried to identify all pediatric admissions (<18 y) with T13 and T18 using International Classification of Diseases, Tenth Revision codes. Therefore, transfers to outside hospital were excluded to avoid systematic double counting. Descriptive statistics were performed (median, [interquartile range]). RESULTS: A total of 582 admissions were identified (181 T13, 401 T18). The majority of admissions occurred in the first year of life. Overall inpatient mortality rates were high in both (T13 27.1%, T18 23.7%) with highest mortality in neonates (≤28 d; T13 65.6%, T18 56.4%). Notably, inpatient mortality in older admissions dramatically decreased. Across all age groups, length of stay and median charges were highest for infants (29-365 d) (T13 length of stay 17 d [3-31], T18 16 d [5-43]) with frequent operative interventions, which persisted throughout childhood. While cardiovascular anomalies were prevalent in the younger cohort, supportive operative interventions including airway, vascular, and feeding access were the most common procedures. CONCLUSIONS: While T13 and T18 both have high mortality, particularly in infancy, there is survival with persistent health-care utilization and operative needs throughout childhood. This highlights significant long-term health-care needs and evolving surgical indications. Longitudinal care coordination of multidisciplinary surgical care is needed to optimize outcomes of affected patients. | F6: J Surg Res | G6: Journal Article | H6: A | I6: Incluir | J6: A | N6: =HYPERLINK("https://pubmed.ncbi.nlm.nih.gov/42302673/","abrir") -> abrir | O6: =IF(B6 < 2024, FALSE() , TRUE()) -> TRUE
A7: 42437037 | B7: 2026 | C7: Koshida S | D7: Poorer survival in prenatally diagnosed trisomy 18 infants compared with postnatally diagnosed cases: a single-center study. | E7: BACKGROUND: Trisomy 18 is a common autosomal trisomy that is associated with high perinatal and infant mortality rates. With the widespread use of prenatal screening, many cases have been identified. In contrast, when the diagnosis occurs in the late prenatal period, that is, beyond the gestational limit for termination, or postnatally, careful planning for delivery and neonatal care is required. Emerging evidence suggests that intensive neonatal care can prolong survival and that the prenatal diagnosis may influence subsequent treatment choices. However, few studies have directly compared survival according to the timing of the diagnosis while accounting for treatment policy. Therefore, we compared survival between prenatally and postnatally diagnosed infants with trisomy 18, and examined whether diagnostic timing was associated with the selection of intensive care. METHODS: A retrospective study was conducted on 35 cases of trisomy 18 identified at our center between 2005 and 2024, including 25 prenatally diagnosed cases and 10 postnatally diagnosed liveborn infants. Among the prenatally diagnosed cases, 15 resulted in live births. Survival outcomes were compared between prenatally diagnosed liveborn infants (n = 15) and postnatally diagnosed liveborn infants (n = 10), and perinatal characteristics were evaluated. RESULTS: Among all liveborn infants, the Kaplan-Meier estimated 12-month survival rates were 8% (95% CI [0.5%-30.6%]) in the prenatal group and 40% (95% CI [12.3%-67.0%]) in the postnatal group, with poorer survival in the prenatal group (log-rank p = 0.02). Among liveborn infants, an intensive care policy was selected significantly less frequently in the prenatal group than in the postnatal group (33.3% [5/15] vs. 90.0% [9/10], p = 0.01). In an exploratory subgroup analysis of infants who received intensive care, the Kaplan-Meier estimated 12-month survival rates were 20% (95% CI [0.8%-58.2%]) in the prenatal group and 44% (95% CI [13.6%-71.9%]) in the postnatal group. The confidence intervals were wide, and no statistically significant difference in survival was observed between the two groups (log-rank p = 0.30). CONCLUSIONS: Overall survival was poorer among infants with trisomy 18 diagnosed prenatally than among those diagnosed postnatally, and this difference may be partly associated with differences in treatment policies. These findings suggest that treatment policies following prenatal diagnosis may be associated with survival duration in trisomy 18. | F7: PeerJ | G7: Journal Article; Comparative Study | H7: A+B | I7: Incluir | J7: A | M7: Destaque: compara diagnóstico pré-natal e pós-natal. | N7: =HYPERLINK("https://pubmed.ncbi.nlm.nih.gov/42437037/","abrir") -> abrir | O7: =IF(B7 < 2024, FALSE() , TRUE()) -> TRUE
A8: 42599515 | B8: 2026 | C8: Nagao H | D8: Survival Benefit and Persistent Hospitalization Burden After Ventricular Septal Defect Closure in Infants with Trisomy 18 Headings: Hospitalization After VSD Closure in Trisomy 18. | E8: This retrospective study evaluated the impact of ventricular septal defect (VSD) closure on long-term survival and hospitalization status in infants with trisomy 18. Thirty-three infants with trisomy 18 and VSD (2002-2025) were categorized into three groups: staged VSD closure following pulmonary artery banding (PAB) (n = 7), PAB alone (n = 3), or non-surgical management (n = 23). Median follow-up durations (interquartile range) were 124.6 (75.8-153.1), 17.8 (11.4-18.1), and 17.1 (2.7-59.3) months, respectively. Kaplan-Meier analysis demonstrated significantly better survival in the VSD closure group (log-rank p = 0.009). However, these survivors required frequent unexpected hospitalizations for non-cardiac comorbidities. In univariate negative binomial regression, respiratory and digestive complications were significantly associated with higher unexpected admission rates (incidence rate ratio [IRR] = 1.07, 95% confidence interval [CI]: 1.02-1.12; and IRR = 1.24, 95% CI: 1.08-1.41, respectively; p < 0.01). After multivariable adjustment, only digestive complications showed a notable, though non-significant, trend (IRR = 1.15, 95% CI: 0.98-1.36, p = 0.09). Notably, VSD closure was associated with a higher admission rate in univariate analysis (IRR = 1.95, 95% CI: 0.95-4.00, p = 0.07), but this association disappeared after multivariable adjustment. VSD closure was associated with improved survival in infants with trisomy 18, but a substantial hospitalization burden persisted due to non-cardiac comorbidities. These findings highlight the importance of lifelong multidisciplinary care and detailed parental counseling regarding the expected long-term medical burden following VSD closure. | F8: Pediatr Cardiol | G8: Journal Article | H8: A | I8: Incluir | J8: A | N8: =HYPERLINK("https://pubmed.ncbi.nlm.nih.gov/42599515/","abrir") -> abrir | O8: =IF(B8 < 2024, FALSE() , TRUE()) -> TRUE
A9: 42634104 | B9: 2026 | C9: Rodriguez LC | D9: Congenital Heart Disease Associated With Genetic Syndromes and Extracardiac Anomalies: A Six-Year Epidemiological Study in a Brazilian Referral Center. | E9: BACKGROUND: Congenital heart diseases (CHDs) are structural and/or functional abnormalities of the heart that arise during embryonic cardiovascular development. They are the most common type of congenital defect and represent a major cause of neonatal morbidity and mortality, particularly when associated with genetic syndromes or other congenital anomalies. This study aims to analyze the clinical and epidemiological profile of CHD in newborns at a high fetal-risk maternity hospital in Rio de Janeiro from 2018 to 2023, describing the types of CHD, associated anomalies and genetic syndromes, maternal risk factors, and neonatal outcomes. METHODS: This is a descriptive, retrospective study using the database of the Latin American Collaborative Study of Congenital Malformations (ECLAMC) at Instituto Fernandes Figueira/Fiocruz (IFF/Fiocruz). Newborns with a confirmed diagnosis of CHD, born at IFF between January 2018 and December 2023 and properly registered in the ECLAMC program were included. RESULTS: Among 5647 births, 225 newborns with CHD were identified and analyzed, corresponding to a prevalence of approximately 4%. The most frequent CHD was ventricular septal defect (VSD), present in 68 cases, followed by atrioventricular septal defect (AVSD) in 41 cases and coarctation of the aorta (CoA) in 27. Complex cardiopathies predominated, representing 60% of cases. Most diagnoses were established prenatally (93.3%), with a fetal echocardiogram accuracy of 78.5%. Associated congenital anomalies were identified in 64% of cases, predominantly affecting the gastrointestinal tract, central nervous system, and genitourinary tract. Genetic syndromes were confirmed in 95 patients (42.2%), with a predominance of Down syndrome (35), followed by Edwards syndrome (29) and Patau syndrome (10). The rate of hospital discharge alive was 53.3% in patients with isolated CHD, compared to 29% in those with associated syndromes or anomalies. CONCLUSIONS: IFF presents a highly complex patient profile, with a high prevalence of CHD associated with genetic syndromes and extracardiac anomalies, reflecting its role as a tertiary referral center. The presence of associated anomalies and syndromes negatively impacted neonatal prognosis, reinforcing the importance of prenatal diagnosis and specialized multidisciplinary care in the management of these conditions. | F9: Birth Defects Res | G9: Journal Article | H9: A | I9: Incluir | J9: A | M9: Verificar no texto completo se há dado específico e separável da T18 | N9: =HYPERLINK("https://pubmed.ncbi.nlm.nih.gov/42634104/","abrir") -> abrir | O9: =IF(B9 < 2024, FALSE() , TRUE()) -> TRUE
A10: 42746679 | B10: 2026 | C10: Fonseca Queiroz L | D10: Intensive versus comfort-focused care in neonates with trisomy 18: A systematic review and meta-analysis. | E10: ObjectiveTo evaluate whether intensive neonatal interventions improve survival outcomes compared with comfort-focused care in neonates with Trisomy 18.Study designWe conducted a systematic review and pairwise meta-analysis of observational studies reporting outcomes for neonates with Trisomy 18 receiving either intensive or comfort-focused care. Databases searched included PubMed, Embase, and Cochrane Central Register up to March 2026. Outcomes included mean survival days and 1-year survival as primary outcomes, and gestational age at delivery as a secondary exploratory outcome.ResultsFive observational studies including 211 patients were analyzed (133 received intensive care, and 78 received comfort-focused care). Pooled analyses showed no statistically significant differences between groups for mean survival days (MD -225.53 days; 95% CI -776.85 to 325.79), 1-year survival (RR 1.12; 95% CI 0.90 to 1.40), or gestational age at birth (MD -0.28 weeks; 95% CI -1.69 to 1.13).ConclusionDespite the absence of a demonstrated survival benefit of intensive neonatal interventions over non-intensive care in Trisomy 18, the findings should be interpreted cautiously given the small number of available studies, substantial clinical and statistical heterogeneity, and very low certainty of evidence. Findings highlight the importance of individualized, informed decision-making guided by prenatal counseling that integrates evidence-based outcomes and parental values. High-quality, multicenter prospective studies are needed to evaluate the impact of specific interventions and improve guidance for families and clinicians. | F10: J Neonatal Perinatal Med | G10: Journal Article; Review | H10: A | I10: Incluir | J10: A | M10: Destaque: revisão sistemática com metanálise mais recente (set/2026), cuidado intensivo x cuidado de conforto. | N10: =HYPERLINK("https://pubmed.ncbi.nlm.nih.gov/42746679/","abrir") -> abrir | O10: =IF(B10 < 2024, FALSE() , TRUE()) -> TRUE
A11: 42764676 | B11: 2026 | C11: Matsushima A | D11: Acute Healthcare Utilization During the First Year After Hospital Discharge in Children With Trisomy 18. | E11: Survival of infants with trisomy 18 (T18) has improved with advances in neonatal intensive care and surgical management, yet postdischarge outcomes remain poorly characterized. This single-center retrospective cohort study included infants with T18 admitted to a Level III neonatal intensive care unit between 2008 and 2022. Survival and survival-to-discharge rates were analyzed by birth era. For patients discharged alive in the most recent era (2018-2022), emergency department (ED) visits and hospital admissions during the first year after discharge were evaluated. Among 87 infants with confirmed outcomes, overall survival and survival-to-discharge rates improved over time. Sixteen patients discharged alive in the late cohort were included in the postdischarge analysis. During the first year after discharge, 13 patients (81%) visited the ED at least once, and 11 (69%) required hospital admission. Respiratory disorders were the most frequent reason for admission, followed by urinary tract infections and gastrointestinal disorders. An exploratory analysis found no significant association between tracheostomy status and ED visits or hospital admissions. Two patients died within 1 year after discharge. Despite improving survival, infants with T18 experience substantial healthcare utilization after discharge, underscoring the need for structured multidisciplinary follow-up and robust home-based care support systems. | F11: Am J Med Genet A | G11: Journal Article | H11: A | I11: Incluir | J11: A | N11: =HYPERLINK("https://pubmed.ncbi.nlm.nih.gov/42764676/","abrir") -> abrir | O11: =IF(B11 < 2024, FALSE() , TRUE()) -> TRUE
A12: 39821650 | B12: 2025 | C12: Visconti D | D12: Trisomy 18 and the possibility of choice: The importance of Perinatal Hospice's support. | E12: Trisomy 18 is a severe aneuploidy associated with multiple malformations and a poor prognosis. The diagnosis is typically made prenatally, leading to a high rate of pregnancy terminations. The aim of this study is to demonstrate that even though the prognosis is heterogeneous, prolonged survival is possible and these children are an enrichment for their families after all. A retrospective, descriptive and monocentric study was conducted on fetuses diagnosed with trisomy 18, evaluated between March 2017 and June 2023 at our Institution. The objective was to investigate the natural history of trisomy 18 and the psychological impact on parents who choose to carry the pregnancy on, through a retrospective data collection and the use of a questionnaire. Sixteen couples with a diagnosis of trisomy 18 were cared for within the Perinatal Hospice Pathway during the study period. Cardiac defects were identified in 93.7% of cases, structural abnormalities in 71.4%, respiratory defects in 14.3% of the fetuses, while genitourinary defects affected nearly half of the study population. The survival rate was typically less than one day, however two babies survived for more than four years. All couples reported being satisfied with their decision to continue the pregnancy and would do so again if given the opportunity.Conclusions: despite the severity of the diagnosis, couples may choose to continue the pregnancy and give birth. Our study shows that trisomy 18 is not merely a lethal condition and the Perinatal Hospice plays a crucial role in supporting these families. | F12: Eur J Pediatr | G12: Journal Article | H12: A+B | I12: Incluir | J12: A+B | N12: =HYPERLINK("https://pubmed.ncbi.nlm.nih.gov/39821650/","abrir") -> abrir | O12: =IF(B12 < 2024, FALSE() , TRUE()) -> TRUE
A13: 39854275 | B13: 2025 | C13: Nemoto S | D13: Closure of ventricular septal defect in children with trisomy 18: perioperative events and long-term survival. | E13: OBJECTIVES: This retrospective study aimed to investigate the feasibility of surgical closure of ventricular septal defect in children with trisomy 18 by assessing perioperative events and long-term survival. METHODS: From April 2008 to March 2024, 41 consecutive patients were referred to us for ventricular septal defect surgery. The defect was closed in 35 patients at the end (median age, 16 months; median body weight, 5.7 kg), 31 out of 37 patients after the preceding pulmonary artery banding according to our staged surgery policy and 4 patients without the banding. Sixty-five significant non-cardiac lesions existed concurrently, and 14 patients underwent tracheostomy before closure. The investigation was conducted by checking medical records and contacting the primary physician. RESULTS: Four patients died during the inter-stage after banding to closure (10.8%). Two of them were awaiting closure. Concomitant surgeries, 15 right ventricular muscle resections, or 1 arch repair, were performed along with closure. Arrhythmia was the most common adverse event (51.4%). Three patients required extracorporeal membrane oxygenation support. Transient but severe hepatic injury occurred in 11 patients (31.4%). There were two hospital death (5.7%) due to severe respiratory insufficiency or fulminant sepsis. Five patients died after discharge, three pneumonia and two sudden death, resulting in a 5-year estimated survival of 79.5%. Three hepatoblastoma and one hepatoangioma developed, but complete remission was achieved in all patients. CONCLUSIONS: Although further studies are mandatory, surgical closure of ventricular septal defect may be an effective treatment option even for children with trisomy 18. | F13: Interdiscip Cardiovasc Thorac Surg | G13: Journal Article | H13: A | I13: Incluir | J13: A | N13: =HYPERLINK("https://pubmed.ncbi.nlm.nih.gov/39854275/","abrir") -> abrir | O13: =IF(B13 < 2024, FALSE() , TRUE()) -> TRUE
A14: 39937286 | B14: 2025 | C14: Zanin A | D14: Early assessment of clinical complexity and home care in patients affected by trisomy 13 and 18. | E14: PURPOSE: Trisomy 13 and 18 consist of a recurrent pattern of multiple congenital anomalies. The aim of this study was to analyze the clinical characteristics and disease trajectory of a cohort of children with trisomy 13 and 18 followed up by an Italian pediatric palliative care service. METHODS: A single-center retrospective observational study was conducted examining the medical records of patients with trisomy 13 and 18 seen in the Pediatric Palliatives Care (PPC) center of the University Hospital of Padua from 2007 to 2022. RESULTS: Seventeen patients were included in the analysis. All were born alive; four children are still alive and only three (23%) died at home. All presented high care complexity, as estimated by ACCAPED index (median 86, range 38-129). The median time to receive care from PPC was 3 months (0-108). All patients' parents shared an advance care plan with the PPC team: 13/17 patients (76%) accepted a do not resuscitate (DNR) order. Approximately 12% of patients received at least one surgery. The trend of survival compared with other cohorts reported in the literature does not appear to differ significantly after the initial stages. CONCLUSIONS: The possible recognition of an early evolution toward medical complexity and the availability of home care resources and programs are crucial factors in the management of these children. These indices could become a driving factor in the definition of new outcomes that are more patient-oriented, in addition to mortality. WHAT IS KNOWN: • Trisomy 13 and 18 are serious genetic conditions with high mortality rates. In the last years medical interventions including surgery are being offered more frequently, though the appropriateness of these interventions is still debated. WHAT IS NEW: • The study emphasizes the crucial role of early referral to specialized pediatric palliative care teams and the coordination they provide enabling families to care for their children at home, even with complex medical needs. | F14: Eur J Pediatr | G14: Journal Article; Observational Study | H14: A | I14: Incluir | J14: A | N14: =HYPERLINK("https://pubmed.ncbi.nlm.nih.gov/39937286/","abrir") -> abrir | O14: =IF(B14 < 2024, FALSE() , TRUE()) -> TRUE
A15: 40010013 | B15: 2025 | C15: Mannava SV | D15: Gastrostomy Tube Placement in Patients With Trisomy 13 and 18: Surgical Decision Making and Outcomes. | E15: PURPOSE: Trisomy 13 (T13) and trisomy 18 (T18) are chromosomal abnormalities which portend high rates of feeding dysfunction and infant mortality risk. Although gastrostomy tube (GT) placement is commonly performed in this population, there is limited data assessing outcomes associated with this procedure. Our aim was to determine survival outcomes among GT and non-GT patients with T13/18. METHODS: We performed a retrospective cohort study of patients with T13 and T18 treated at our institution from 2005 through 2020. We compared baseline characteristics and survival data between GT and non-GT patients and performed multivariable survival analysis. RESULTS: We analyzed a total of 86 patients (23 GT, 63 non-GT). Over one-third of GT patients underwent the procedure during initial admission and most GTs were used for longer than one year (60.9 %). Significantly more GT patients survived initial discharge (87 % vs. 57.1 %, p < 0.001) and were alive at follow-up (43.5 % vs. 6.3 %, p < 0.001) compared to non-GT patients. Thirty-day post-discharge survival was determined solely by GT status and not impacted by predictors. GT patients had reduced overall mortality risk compared to non-GT patients in the first year of life (HR = 0.10 [95 % CI 0.04-0.29], p < 0.001) and during the fifteen-year study period (HR = 0.15 [95 % CI 0.06-0.35], p < 0.001). CONCLUSIONS: GT status predicted 30-day post-discharge survival in our cohort. GT patients had reduced overall mortality risk compared to non-GT patients. In patients with expected survival to initial discharge and feeding difficulty, GT placement at or after initial admission may be associated with improved survival outcomes. LEVEL OF EVIDENCE: III. | F15: J Pediatr Surg | G15: Journal Article | H15: A | I15: Incluir | J15: A | N15: =HYPERLINK("https://pubmed.ncbi.nlm.nih.gov/40010013/","abrir") -> abrir | O15: =IF(B15 < 2024, FALSE() , TRUE()) -> TRUE
A16: 40537699 | B16: 2025 | C16: de Sá Bittencourt Câmara Bastos C | D16: Outcomes of heart surgery in neonates with trisomy 13 and 18: a systematic review with metanalysis. | E16: This systematic review and meta-analysis aimed to evaluate the clinical outcomes of cardiac surgery in neonates with trisomy 13 (T13) or trisomy 18 (T18) compared to those managed with palliative care. A literature search was conducted in PubMed® and EMBASE®, following PRISMA guidelines, and included five retrospective cohort studies (1627 patients). Outcomes analyzed included in-hospital mortality, survival at 12 months, length of stay (LOS), hospital discharge rates, and the need for mechanical ventilation. The meta-analysis showed that cardiac surgery significantly reduced the odds of in-hospital mortality (OR 0.12, CI 95% 0.03-0.42, p < 0.01), increased survival at 12 months (OR 19.77, CI 95% 5.12-76.36, p < 0.01), and improved discharge rates (OR 12.53, CI 95% 3.63-43.22, p < 0.01). However, limited data were available on quality of life and mechanical ventilation duration. Conclusion: Despite the positive impact of cardiac surgery on survival and discharge rates, the evidence remains low quality, as the included studies were primarily retrospective cohorts with moderate risk of bias. The findings highlight the importance of involving families in the decision-making process, given their differing perspectives on quality of life. Further high-quality studies, such as randomized controlled trials, are needed to provide stronger evidence on this topic. | F16: Eur J Pediatr | G16: Journal Article; Systematic Review; Meta-Analysis | H16: A | I16: Incluir | J16: A | N16: =HYPERLINK("https://pubmed.ncbi.nlm.nih.gov/40537699/","abrir") -> abrir | O16: =IF(B16 < 2024, FALSE() , TRUE()) -> TRUE
A17: 40599664 | B17: 2025 | C17: Armour E | D17: Liveborn children with trisomy 18: A retrospective review. | E17: BACKGROUND: Historically, children born alive with trisomy 18 were considered to have a lethal genetic condition such that no medical interventions were provided. While survival is now recognized to be possible, these children's lives include aspects of technological dependency, medical complexity, and neurodevelopmental disabilities. OBJECTIVES: The primary aim of this study was to describe the outcomes of a contemporary Canadian population-based cohort of children born alive with trisomy 18. METHODS: A retrospective study was conducted to review the records of children born alive with trisomy 18 from January 2012 to December 2023 in Central/Northern Alberta. Demographic and clinical information were abstracted, including features reported in the literature associated with morbidity and mortality. Outcomes were described, including technological dependency, time spent in the hospital, and survival. RESULTS: In total, 37 liveborn infants with complete trisomy 18 were identified. While most died in hospital following medical-surgical interventions and/or comfort-care palliation, nine were discharged home. All of these children had been born at term with a birthweight ≥1750 g. While they relied on medical technologies such as home oxygen and feeding tubes at the time of discharge, most were able to spend a considerable amount of time at home rather than being re-hospitalized. At the time of this review, four remain alive varying in age from 6 to 9 years. CONCLUSIONS: Trisomy 18 is not a homogeneous clinical condition. Some children may have their lives extended to spend their lives at home with their families. | F17: Paediatr Child Health | G17: Journal Article | H17: A | I17: Incluir | J17: A | N17: =HYPERLINK("https://pubmed.ncbi.nlm.nih.gov/40599664/","abrir") -> abrir | O17: =IF(B17 < 2024, FALSE() , TRUE()) -> TRUE
A18: 40920381 | B18: 2025 | C18: Ludorf KL | D18: Long-Term Survival Among Children With Trisomy 13 and Trisomy 18 by Cytogenetic Status. | E18: IMPORTANCE: Trisomy 13 (T13) and trisomy 18 (T18) are chromosomal abnormalities with high mortality rates in the first year of life. Understanding differences in long-term survival between children with full vs mosaic or partial trisomy is crucial for prognosis and health care planning. OBJECTIVE: To examine the differences in 10-year survival between children with full T13 and T18 vs those with mosaic or partial trisomy. DESIGN, SETTING, AND PARTICIPANTS: This retrospective, population-based cohort study assessed liveborn infants with T13 and T18 in the Texas Birth Defects Registry (deliveries from January 1, 1999, to December 31, 2008). Follow-up was through December 31, 2018 (the last date available at the time of analyses) to allow for 10 years of follow-up for all infants. All analyses were conducted from January 1, 2022, to December 31, 2024. EXPOSURES: Cytogenetic status (full trisomy vs mosaic or partial trisomy). MAIN OUTCOMES AND MEASURES: The primary outcome was survival to 10 years of age, assessed using Kaplan-Meier survival estimates. The association between cytogenetic status and mortality by 10 years of age was assessed using Cox proportional hazards regression to generate hazard ratios (HRs). Population attributable fraction was calculated to determine the percentage of survival attributable to mosaic or partial trisomy status. RESULTS: The study cohort included 798 infants (463 female infants [58.0%]; mean [SD] maternal age, 30.9 [8.0] years) with T13 (n = 295) or T18 (n = 503). Among all cases with T13, 25 infants (8.5%; 95% CI, 5.5%-12.3%) survived to 10 years of age. Similarly, among all infants with T18, 43 (8.6%; 95% CI, 6.3%-11.3%) survived to 10 years of age. Kaplan-Meier survival estimates to 10 years of age were statistically significantly higher among children with mosaic or partial trisomy (13 [25.0%] and 14 [43.8%], respectively) compared with full trisomy (12 [4.9%] and 29 [6.6%], respectively) (both P < .001). Infants with full trisomy had statistically significantly increased 10-year mortality hazards compared with those with mosaic or partial trisomy for both T13 (HR, 2.00; 95% CI, 1.42-2.82) and T18 (HR, 3.34; 95% CI, 2.08-5.38). The results of the calculated proportion of 10-year survival due to the presence of nonfull trisomy status (population attributable fraction) was 41.7% for children with T13 and 27.9% for children with T18. CONCLUSIONS AND RELEVANCE: The findings of this cohort study of infants with T13 and T18 support differences in long-term survival based on cytogenetic status and emphasize the need to potentially reassess the context of these conditions generally being considered incompatible with life, particularly for those with mosaic trisomies. These findings offer context surrounding treatment decisions, such as withholding interventions, for affected infants in the future. | F18: JAMA Netw Open | G18: Journal Article; Research Support, Non-U.S. Gov't | H18: A | I18: Incluir | J18: A | M18: Sobrevida de longo prazo por status citogenético (completa x mosaico/parcial). | N18: =HYPERLINK("https://pubmed.ncbi.nlm.nih.gov/40920381/","abrir") -> abrir | O18: =IF(B18 < 2024, FALSE() , TRUE()) -> TRUE
A19: 41420650 | B19: 2025 | C19: Reischer T | D19: Clinical course and perinatal management of fetuses and newborns affected by trisomy 13 and 18: a retrospective single-centre cohort study. | E19: Objectives Trisomy 13 (T13) and 18 (T18) are lethal chromosomal abnormalities. While the prognosis is generally poor, recent evidence suggests that some infants with T13 and T18 are able to survive longer than previously supposed. These findings underline the importance of an individualised approach to perinatal/neonatal care. Methods This retrospective study included 193 pregnancies with T13 and T18 in a single tertiary center between 2005 and 2023. Fetal and maternal characteristics, overall survival, and perinatal and postnatal management were analysed. Results Of 193 affected fetuses, 142 (73.6%) were diagnosed with T18 and 51 (26.4%) with T13. Associated malformations were present in 90.7% (175 cases), with congenital heart defects being the most common (42%). A total of 161 (83,4%) women opted for termination of pregnancy (TOP). Gestational age at diagnosis was significantly higher among women opting to continue pregnancy compared to those opting for TOP. Among women continuing pregnancy, 65.6% (21/32) experienced intrauterine fetal death. Eleven pregnancies resulted in live births. Survival times for infants born alive ranged from 6 min to 60 days, with a median survival time of 18 h. Newborns affected by T18 lived significantly longer than those with T13 (median 33 h vs 6.5 h).Conclusion: The duration of survival in infants with T13 and T18 remains highly variable and difficult to predict. Management strategies must therefore be clarified within an interdisciplinary framework, supporting families through informed, individualised decision-making while balancing the poor prognosis with a focus on comfort, dignity, and quality of life. | F19: Eur J Pediatr | G19: Journal Article | H19: A | I19: Incluir | J19: A+B | N19: =HYPERLINK("https://pubmed.ncbi.nlm.nih.gov/41420650/","abrir") -> abrir | O19: =IF(B19 < 2024, FALSE() , TRUE()) -> TRUE
A20: 37822198 | B20: 2024 | C20: Mehl JM | D20: Causes of death in individuals with trisomy 18 after the first year of life. | E20: Mortality in individuals with trisomy 18 has significantly decreased over the past 20 years, but there is scant literature addressing the prognosis and cause of death in individuals with trisomy 18 and survival past the first year of life (YOL). This study analyzed factors associated with mortality and cause of death in a retrospective cohort of 174 individuals with trisomy 18 and survival past the first YOL, the largest such series to date. Data were collected via retrospective survey of parents of affected individuals. Prenatal diagnosis of trisomy 18; postnatal respiratory distress; maternal age > 35 years; birthweight <2000 g; brain and spinal cord defect(s); atrial and/or ventricular septal defect(s); inability to feed orally without medical assistance; and failure to meet sitting and rolling milestones were associated with mortality in this sample. Cause of death was compared between our cohort of individuals with trisomy 18 and existing literature on those with mortality before the first YOL. Individuals with trisomy 18 with mortality after the first YOL demonstrated a predominance of infectious (n = 10/22) and postoperative (n = 6/22) contributing causes of death, in contrast to the existing literature, which shows a predominance of cardiopulmonary causes of death (e.g., cardiopulmonary arrest, pulmonary hypertension). These findings demonstrate that individuals with trisomy 18 and survival past the first YOL have unique medical needs, but further research is needed to develop clinical guidelines for this growing population. | F20: Am J Med Genet A | G20: Journal Article | H20: A+B | I20: Incluir | J20: A | M20: Destaque: maior série de sobreviventes além de 1 ano (174; questionário de pais). Diagnóstico pré-natal entre os fatores associados à mortalidade. | N20: =HYPERLINK("https://pubmed.ncbi.nlm.nih.gov/37822198/","abrir") -> abrir | O20: =IF(B20 < 2024, FALSE() , TRUE()) -> TRUE
A21: 38071520 | B21: 2024 | C21: Kutsukake M | D21: Treatment courses and outcomes of oesophageal atresia in patients with trisomy 18: a case series of 271 patients from a nationwide database in Japan. | E21: OBJECTIVE: To describe characteristics, treatments and clinical outcomes of patients with trisomy 18 and oesophageal atresia, using a nationwide database in Japan. DESIGN: Descriptive study using a retrospective cohort. SETTING: A nationwide inpatient database including 90% of hospitals with neonatal intensive care units in Japan. PATIENTS: Patients hospitalised within a day after birth for both oesophageal atresia and trisomy 18 between July 2010 and March 2020. INTERVENTIONS: Radical surgery for oesophageal atresia. MAIN OUTCOME MEASURES: Characteristics, treatment course and outcomes. RESULTS: Among 271 patients with both oesophageal atresia and trisomy 18, 70 patients underwent radical surgery for oesophageal atresia. Patients who underwent radical surgery were less likely to have severe cardiac anomalies (17% vs 32%; p=0.020), but more likely to undergo cardiac surgery (21% vs 9.5%; p=0.012) than those who did not. The overall in-hospital mortality was lower (54% vs 79%; p<0.001) and the median age at death was higher (210 days vs 39 days; p<0.001) in patients who underwent radical surgery than the others. Postoperative mortality within 30 days after radical surgery was 5.7%. Patients who underwent radical surgery were likely to be discharged to home (50% vs 18%; p<0.001), whereas the age at home discharge (median 314 days vs 216 days; p=0.19) and the requirement for each home treatment did not differ significantly by radical surgery. CONCLUSION: This study provides information that will aid the clinical decision-making process for patients with oesophageal atresia and trisomy 18. Radical surgery may be a safe and feasible treatment option. | F21: Arch Dis Child Fetal Neonatal Ed | G21: Journal Article | H21: A | I21: Incluir | J21: A | N21: =HYPERLINK("https://pubmed.ncbi.nlm.nih.gov/38071520/","abrir") -> abrir | O21: =IF(B21 < 2024, FALSE() , TRUE()) -> TRUE
A22: 38340889 | B22: 2024 | C22: Greenberg JW | D22: Contemporary Trends in Cardiac Surgical Care for Trisomy 13 and 18 Patients Admitted to Hospitals in the United States. | E22: OBJECTIVE: To assess rates of cardiac surgery and the clinical and demographic features that influence surgical vs nonsurgical treatment of congenital heart disease (CHD) in patients with trisomy 13 (T13) and trisomy 18 (T18) in the United States. STUDY DESIGN: A retrospective study was performed using the Pediatric Health Information System. All hospital admissions of children (<18 years of age) with T13 and T18 in the United States were identified from 2003 through 2022. International Classifications of Disease (ICD) codes were used to identify presence of CHD, extracardiac comorbidities/malformations, and performance of cardiac surgery. RESULTS: Seven thousand one hundred thirteen patients were identified. CHD was present in 62% (1625/2610) of patients with T13 and 73% (3288/4503) of patients with T18. The most common CHD morphologies were isolated atrial/ventricular septal defects (T13 40%, T18 42%) and aortic hypoplasia/coarctation (T13 21%, T18 23%). Single-ventricle morphologies comprised 6% (100/1625) of the T13 and 5% (167/3288) of the T18 CHD cohorts. Surgery was performed in 12% of patients with T13 plus CHD and 17% of patients with T18 plus CHD. For all cardiac diagnoses, <50% of patients received surgery. Nonsurgical patients were more likely to be born prematurely (P < .05 for T13 and T18). The number of extracardiac comorbidities was similar between surgical/nonsurgical patients with T13 (median 2 vs 2, P = .215) and greater in surgical vs nonsurgical patients with T18 (median 3 vs 2, P < .001). Hospital mortality was <10% for both surgical cohorts. CONCLUSIONS: Patients with T13 or T18 and CHD receive surgical palliation, but at a low prevalence (≤17%) nationally. Given operative mortality <10%, opportunity exists perhaps for quality improvement in the performance of cardiac surgery for these vulnerable patient populations. | F22: J Pediatr | G22: Journal Article | H22: A | I22: Incluir | J22: A | N22: =HYPERLINK("https://pubmed.ncbi.nlm.nih.gov/38340889/","abrir") -> abrir | O22: =IF(B22 < 2024, FALSE() , TRUE()) -> TRUE
A23: 38884184 | B23: 2024 | C23: Tamaki S | D23: Impact of definitive surgery for esophageal atresia on long-term outcomes in patients with trisomy 18. | E23: This study investigates the long-term outcomes of palliative and definitive surgeries for esophageal atresia (EA) in patients with trisomy 18 syndrome. A retrospective study included 25 cases undergoing EA surgery at our center between 2008 and 2022. The Palliative group (n = 16) comprised 13 cases with esophageal banding and 3 with tracheoesophageal fistula (TEF) division. The Definitive group (n = 9) included 5 cases with primary repair and 4 with staged repair following TEF division. The patient characteristics exhibited no significant differences between the groups. In the Definitive group, 56% (5/9) were successfully weaned off mechanical ventilation, compared with none in the Palliative group (p = 0.002). Survival-to-discharge rates were 31% (5/16) in the Palliative group and 67% (6/9) in the Definitive group. Home ventilator management was required for all 5 cases that required ventilation in the Palliative group, whereas only 17% (1/6) in the Definitive group needed it. The Palliative group also required continuous oral suction for persistent saliva removal, with two cases undergoing laryngotracheal separation. Overall, definitive surgery for EA in patients with trisomy 18 syndrome may provide enhanced respiratory stability, thereby improving the survival-to-discharge rate and overall quality of life for patients and their families. | F23: Am J Med Genet A | G23: Journal Article | H23: A | I23: Incluir | J23: A | N23: =HYPERLINK("https://pubmed.ncbi.nlm.nih.gov/38884184/","abrir") -> abrir | O23: =IF(B23 < 2024, FALSE() , TRUE()) -> TRUE
A24: 39296445 | B24: 2024 | C24: Greene CL | D24: Operative and nonoperative outcomes in patients with trisomy 13 and 18 with congenital heart disease. | E24: OBJECTIVE: To evaluate the short- and long-term outcomes of cardiac repair versus nonoperative management in patients with trisomy 13 and trisomy 18 with congenital heart disease. METHODS: An institutional review board-approved, retrospective review was undertaken to identify all patients admitted with trisomy 13/18 and congenital heart disease. Patients were divided into 2 cohorts (operated vs nonoperated) and compared. RESULTS: Between 1985 and 2023, 62 patients (34 operated and 28 nonoperated) with trisomy 13 (n = 9) and trisomy 18 (n = 53) were identified. The operated cohort was 74% girls, underwent mainly The Society of Thoracic Surgeons-European Association for Cardio-Thoracic Surgery mortality category 1 procedures (n = 24 [71%]) at a median age of 2.5 months (interquartile range [IQR], 1.3-4.5 months). This compares with the nonoperative cohort where 64% (n = 18) would have undergone The Society of Thoracic Surgeons-European Association for Cardio-Thoracic Surgery mortality category 1 procedures if surgery would have been elected. The most common diagnosis was ventricular septal defect. Postoperative median intensive care unit stay was 6.5 days (IQR, 3.7-15 days) with a total hospital length of stay of 15 days (IQR, 11-49 days). Thirty-day postoperative survival was 94%. There were 5 in-hospital deaths in the operated and 7 in the nonoperated cohort. Median follow-up was 15.4 months (IQR, 4.3-48.7 months) for the operated and 11.2 months (IQR, 1.2-48.3 months) for the nonoperated cohorts. One-year survival was 79% operated versus 51.5% nonoperated (P < .003). Nonoperative treatment had an increased risk of mortality (hazard ratio, 3.28; 95% CI, 1.46-7.4; P = .004). CONCLUSIONS: Controversy exists regarding the role of primary cardiac repair in patients with trisomy 13/18 and congenital heart disease. Cardiac repair can be performed safely with low early mortality and operated patients had higher long-term survival compared with nonoperated in our cohort. | F24: JTCVS Open | G24: Journal Article | H24: A | I24: Incluir | J24: A | N24: =HYPERLINK("https://pubmed.ncbi.nlm.nih.gov/39296445/","abrir") -> abrir | O24: =IF(B24 < 2024, FALSE() , TRUE()) -> TRUE
A25: 40016985 | B25: 2024 | C25: Schlosser MP | D25: Liveborn children with trisomy 18: A scoping review. | E25: BACKGROUND: There have been an increasing number of publications related to trisomy 18 associated with a shift in the philosophy of care. The objective of this review is to understand the scope of contemporary literature informing the care of children born alive with trisomy 18. METHODS: Included was peer-reviewed, primary literature in MEDLINE, Embase, CINAHL, Scopus, Web of Science, and Cochrane Library from 2012 to 2023 reporting outcomes of children born alive with trisomy 18. Data extraction involved descriptive statistics of the types of studies, and an inductive thematic analysis of the questions addressed by the studies. RESULTS: Of 4628 records identified, 229 met inclusion criteria. Key themes were organized around the domains: What is trisomy 18? What are the chances of survival with trisomy 18? What can be done to improve the chances of survival with trisomy 18? How do children with trisomy 18 die? Do surgical interventions provide a benefit? Are there non-surgical options? What knowledge is informing medical management? How is life described for children with trisomy 18? What are children with trisomy 18 like as babies and as they get older? What is life like for families caring for children with trisomy 18? CONCLUSIONS: A sizeable number of publications grouped trisomy 18 with other syndromes. Relatively few showed the longitudinal evolution of medical issues associated with trisomy 18, nor did they unfold the clinical heterogeneity of this population. This review shows the limited knowledge base guiding decision-making and care for children born alive with trisomy 18. | F25: J Neonatal Perinatal Med | G25: Journal Article; Scoping Review | H25: A | I25: Incluir | J25: A | M25: Destaque: revisão de escopo sobre nascidos vivos com T18. | N25: =HYPERLINK("https://pubmed.ncbi.nlm.nih.gov/40016985/","abrir") -> abrir | O25: =IF(B25 < 2024, FALSE() , TRUE()) -> TRUE
A26: 36402594 | B26: 2023 | C26: Hafezi N | D26: Surgical History and Outcomes in Trisomy 13 and 18: A Thirty-year Review. | E26: BACKGROUND: Patients with Trisomy 13(T13) and 18(T18) have many comorbidities that may require surgical intervention. However, surgical care and outcomes are not well described, making patient selection and family counseling difficult. Here the surgical history and outcomes of T13/ T18 patients are explored. METHODS: A retrospective review of patients with T13 or T18 born between 1990 and 2020 and cared for at a tertiary children's hospital (Riley Hospital for Children, Indianapolis IN) was conducted, excluding those with insufficient records. Primary outcomes of interest were rates of mortality overall and after surgery. Factors that could predict mortality outcomes were also assessed. RESULTS: One-hundred-seventeen patients were included, with 65% T18 and 35% T13. More than half of patients(65%) had four or more comorbidities. Most deaths occurred by three months at median 42.0 days. Variants of classic trisomies (mosaicism, translocation, partial duplication; p = 0.001), higher birth weight(p = 0.002), and higher gestational age(p = 0.01) were associated with lower overall mortality, while cardiac(p = 0.002) disease was associated with higher mortality. Over half(n = 64) underwent surgery at median age 65 days at time of first procedure. The most common surgical procedures were general surgical. Median survival times were longer in surgical rather than nonsurgical patients(p<0.001). Variant trisomy genetics(p = 0.002) was associated with lower mortality after surgery, while general surgical comorbidities(p = 0.02), particularly tracheoesophageal fistula/esophageal atresia(p = 0.02), were associated with increased mortality after surgery. CONCLUSIONS: Trisomy 13 and 18 patients have vast surgical needs. Variant trisomy was associated with lower mortality after surgery while general surgical comorbidities were associated with increased mortality after surgery. Those who survived to undergo surgery survived longer overall. LEVEL OF EVIDENCE: III. | F26: J Pediatr Surg | G26: Journal Article | H26: A | I26: Incluir | J26: A | N26: =HYPERLINK("https://pubmed.ncbi.nlm.nih.gov/36402594/","abrir") -> abrir | O26: =IF(B26 < 2024, FALSE() , TRUE()) -> FALSE
A27: 36776116 | B27: 2023 | C27: Mizrahi M | D27: Trisomy 18: disparities of care and outcomes in the State of Texas between 2009 and 2019. | E27: OBJECTIVE: To perform a statewide characteristics and outcomes analysis of the Trisomy 18 (T18) population and explore the potential impact of associated congenital heart disease (CHD) and congenital heart surgery. STUDY DESIGN: Retrospective review of the Texas Hospital Inpatient Discharge Public Use Data File between 2009 and 2019, analysing discharges of patients with T18 identified using ICD-9/10 codes. Discharges were linked to analyse patients. Demographic characteristics and available outcomes were evaluated. The population was divided into groups for comparison: patients with no documentation of CHD (T18NoCHD), patients with CHD without congenital heart surgery (T18CHD), and patients who underwent congenital heart surgery (T18CHS). RESULTS: One thousand one hundred fifty-six eligible patients were identified: 443 (38%) T18NoCHD, 669 (58%) T18CHD, and 44 (4%) T18CHS. T18CHS had a lower proportion of Hispanic patients (n = 9 (20.45%)) compared to T18CHD (n = 315 (47.09%)), and T18NoCHD (n = 219 (49.44%)) (p < 0.001 for both). Patients with Medicare/Medicaid insurance had a 0.42 odds ratio (95%CI: 0.20-0.86, p = 0.020) of undergoing congenital heart surgery compared to private insurance. T18CHS had a higher median total days in-hospital (47.5 [IQR: 12.25-113.25] vs. 9 [IQR: 3-24] and 2 [IQR: 1-5], p < 0.001); and a higher median number of admissions (n = 2 [IQR: 1-4]) vs. 1 [IQR: 1-2] and 1 [IQR: 1-1], (p < 0.001 for both). However, the post-operative median number of admissions for T18CHS was 0 [IQR: 0-2]. After the first month of life, T18CHS had freedom from in-hospital mortality similar to T18NoCHD and superior to T18CHD. CONCLUSIONS: Short-term outcomes for T18CHS patients are encouraging, suggesting a freedom from in-hospital mortality that resembles the T18NoCHD. The highlighted socio-economic differences between the groups warrant further investigation. Development of a prospective registry for T18 patients should be a priority for better understanding of longer-term outcomes. | F27: Cardiol Young | G27: Journal Article | H27: A | I27: Incluir | J27: A | N27: =HYPERLINK("https://pubmed.ncbi.nlm.nih.gov/36776116/","abrir") -> abrir | O27: =IF(B27 < 2024, FALSE() , TRUE()) -> FALSE
A28: 36863687 | B28: 2023 | C28: Bouzaglou A | D28: Management and survival of foetuses with trisomy 18 in a French retrospective cohort. | E28: OBJECTIVES: The main objective of this study was to evaluate parents' current demands following the announcement of trisomy 18 and maternal risks. MATERIAL AND METHODS: A single-centre retrospective study was performed in the Paris Saclay Foetal Medicine Department from 2018 to 2021. All patients followed up in the department who had cytogenetic confirmation of trisomy 18 were included. RESULTS: 89 patients were recruited. The most common malformations at ultrasound examination were cardiac or brain abnormalities, distal arthrogryposis as well as severe intrauterine growth retardation. 29% of foetuses with trisomy 18 had more than three malformations. 77.5% of patients requested medical termination of pregnancy. Among the 19 patients who chose to continue their pregnancy, 10 (52.6%) presented with obstetrical complications, of which 7 (41.2%) experienced stillbirth; five babies were born alive with no survival at 6 months. CONCLUSION: In France, in the case of foetal trisomy 18, most women request termination of pregnancy. In the post-natal period, the management of a newborn with trisomy 18 is oriented towards palliative care. The mother's risk of obstetrical complications should be part of counselling. Follow-up, support and safety should be the goal of management of these patients, regardless of the patient's choice. | F28: J Gynecol Obstet Hum Reprod | G28: Journal Article | H28: A+B | I28: Incluir | J28: A+B | N28: =HYPERLINK("https://pubmed.ncbi.nlm.nih.gov/36863687/","abrir") -> abrir | O28: =IF(B28 < 2024, FALSE() , TRUE()) -> FALSE
A29: 36882305 | B29: 2023 | C29: Glinianaia SV | D29: Ten-year survival of children with trisomy 13 or trisomy 18: a multi-registry European cohort study. | E29: OBJECTIVE: To investigate the survival to 10 years of age of children with trisomy 13 (T13) and children with trisomy 18 (T18), born 1995-2014. DESIGN: Population-based cohort study that linked mortality data to data on children born with T13 or T18, including translocations and mosaicisms, from 13 member registries of EUROCAT, a European network for the surveillance of congenital anomalies. SETTING: 13 regions in nine Western European countries. PATIENTS: 252 live births with T13 and 602 with T18. MAIN OUTCOME MEASURES: Survival at 1 week, 4 weeks and 1, 5 and 10 years of age estimated by random-effects meta-analyses of registry-specific Kaplan-Meier survival estimates. RESULTS: Survival estimates of children with T13 were 34% (95% CI 26% to 46%), 17% (95% CI 11% to 29%) and 11% (95% CI 6% to 18%) at 4 weeks, 1 and 10 years, respectively. The corresponding survival estimates were 38% (95% CI 31% to 45%), 13% (95% CI 10% to 17%) and 8% (95% CI 5% to 13%) for children with T18. The 10-year survival conditional on surviving to 4 weeks was 32% (95% CI 23% to 41%) and 21% (95% CI 15% to 28%) for children with T13 and T18, respectively. CONCLUSIONS: This multi-registry European study found that despite extremely high neonatal mortality in children with T13 and T18, 32% and 21%, respectively, of those who survived to 4 weeks were likely to survive to age 10 years. These reliable survival estimates are useful to inform counselling of parents after prenatal diagnosis. | F29: Arch Dis Child | G29: Journal Article; Research Support, Non-U.S. Gov't | H29: A+B | I29: Incluir | J29: A | N29: =HYPERLINK("https://pubmed.ncbi.nlm.nih.gov/36882305/","abrir") -> abrir | O29: =IF(B29 < 2024, FALSE() , TRUE()) -> FALSE
A30: 37070966 | B30: 2023 | C30: Nowakowska A | D30: Prenatal echocardiography in Trisomy 18 - the key to diagnosis and further management in the second half of pregnancy. | E30: OBJECTIVES: Trisomy 18 is an autosomal chromosomal disorder, which is associated with numerous ranges of congenital anomalies. Purpose of this largest study in Poland was to analyze diagnosis and follow-up of fetuses with the prenatal diagnosis of Trisomy 18 in our tertiary center. MATERIAL AND METHODS: The study was conducted in a tertiary center for fetal cardiology. The inclusion criteria comprised fetuses with karyotype of Trisomy 18. Data on number of delivery, number of pregnancy, cardiac and extracardiac diseases, type and date of childbirth, sex, birth date, Apgar score, survival time and autopsy were analyzed. RESULTS: There were 41 fetuses with diagnosis confirmed by amniocentesis: 34 were females, 7 males. CHD was detected prenatally in 73% cases at mean gestational age of 26 weeks. The most common CHD was AV-canal (13 cases, 43%) and VSD (13 cases, 43%). In 1999-2010 the average time to detect a heart defect was 29 weeks, in 2011-2021 it was 23 weeks (p < 0.01, U-Mann-Whitney). IUGR was diagnosed in the 3rd trimester in 29 cases (70%), polyhydramnion in 21 cases (51%). CONCLUSIONS: Congenital heart defects in female fetuses with intrauterine growth restriction in 3rd trimester with polyhydramnios and in subsequent pregnancy, regardless of maternal age, were typical prenatal findings for Trisomy 18. Heart defects with incomplete septum such as AVC or VSD (which nowadays can be detected in the 1st half of the pregnancy) were the most common anomaly in Edwards Syndrome. These heart defects did not require intervention in the early neonatal period. | F30: Ginekol Pol | G30: Journal Article | H30: A | I30: Incluir | J30: A+B | N30: =HYPERLINK("https://pubmed.ncbi.nlm.nih.gov/37070966/","abrir") -> abrir | O30: =IF(B30 < 2024, FALSE() , TRUE()) -> FALSE
A31: 37210512 | B31: 2023 | C31: Song IG | D31: Survival of children with trisomy 18 associated with the presence of congenital heart disease and intervention in the Republic of Korea. | E31: BACKGROUND: Trisomy 18 syndrome (T18) is the second most common autosomal trisomy and has a high risk of fetal loss and stillbirth. Aggressive surgical treatments for the respiratory, cardiac, or digestive systems of patients with T18 were previously futile, while the results of recent studies are controversial. Over the past decade, there have been approximately 300,000 to 400,000 births annually in the Republic of Korea; however, there have been no nationwide studies on T18. This nationwide retrospective cohort study aimed to determine the prevalence of T18 in Korea and its prognosis according to the presence of congenital heart disease and relevant interventions. METHODS: This study utilized NHIS-registered data between 2008 and 2017. A child was defined as having T18 if the ICD-10 revision code Q91.0-3 was reported. Subgroup analysis was performed for children with congenital heart diseases, and survival rates were compared based on the history of cardiac surgical or catheter interventions. The primary outcomes in this study were the survival rate during the first hospitalization period and the 1-year survival rate. RESULTS: Of the children born between 2008 and 2017, 193 were diagnosed with T18. Of these, 86 died, with a median survival of 127 days. The 1-year survival rate for children with T18 was 63.2%. The survival rate in the first admission of children with T18 who did and did not have congenital heart disease was 58.3% and 94.1%, respectively. Children with heart disease who underwent surgical or catheter intervention had a longer survival time than those who did not. CONCLUSIONS: We suggest these data could be used in ante- and postnatal counseling. Ethical concerns about the prolonged survival of children with T18 remain; however, the potential benefits of interventions for congenital heart disease in this population need further study. | F31: BMC Pediatr | G31: Journal Article | H31: A | I31: Incluir | J31: A | N31: =HYPERLINK("https://pubmed.ncbi.nlm.nih.gov/37210512/","abrir") -> abrir | O31: =IF(B31 < 2024, FALSE() , TRUE()) -> FALSE
A32: 37698299 | B32: 2023 | C32: Takai A | D32: Effectiveness of cardiac palliative surgery for trisomy 18 patients with increased pulmonary blood flow. | E32: Congenital heart disease (CHD) is common among patients with trisomy 18 (T18), but cardiac surgery has been rarely indicated for T18 patients due to their short life span. Although the therapeutic effects of aggressive interventions were recently demonstrated for T18 patients, the subjects and factors examined varied, resulting in inconsistent findings. Therefore, the effects of cardiac surgery for T18 remain unclear. We herein investigated the outcomes of cardiac palliative surgery for CHD with increased pulmonary blood flow in T18 patients. 27 patients were examined: 13 (48.1%) underwent cardiac palliative surgery and 14 (51.9%) did not. Median survival times in the no-surgery and surgery groups were 223.0 days (95% confidence interval [CI]: 46-361 days) and 723.0 days (95% CI: 360-1447 days), respectively. The number of patients with pulmonary hypertension significantly differed between the two groups (5 of 14 in the no-surgery group and 0 in the surgery group). Five of 14 patients in the no-surgery group and 10 of 13 in the surgery group were discharged to home care (odds ratio: 10.8 [95% CI: 1.07-110.0]). Therefore, cardiac palliative surgery may be used to treat CHD with increased pulmonary blood flow in T18 patients. | F32: Am J Med Genet A | G32: Journal Article | H32: A | I32: Incluir | J32: A | N32: =HYPERLINK("https://pubmed.ncbi.nlm.nih.gov/37698299/","abrir") -> abrir | O32: =IF(B32 < 2024, FALSE() , TRUE()) -> FALSE
A33: 37821084 | B33: 2023 | C33: Lee JA | D33: Major Congenital Anomalies in Korean Livebirths in 2013-2014: Based on the National Health Insurance Database. | E33: BACKGROUND: In Korea, there have been no reports comparing the prevalence of major congenital anomalies with other countries and no reports on surgical treatment and long-term mortality. We investigated the prevalence of 67 major congenital anomalies in Korea and compared the prevalence with that of the European network of population-based registries for the epidemiological surveillance of congenital anomalies (EUROCAT). We also investigated the mortality and age at death, the proportion of preterm births, and the surgical rate for the 67 major congenital anomalies. METHODS: Korean National Health Insurance claim data were obtained for neonates born in 2013-2014 and admitted within one-year-old. Sixty-seven major congenital anomalies were defined by medical diagnoses classified by International Classification of Diseases-10 codes according to the EUROCAT definition version 2014. Mortality and surgery were defined if any death or surgery claim code was confirmed until 2020. Poisson distribution was used to calculate the 95% confidence interval of the congenital anomaly prevalence. RESULTS: The total prevalence of the 67 major anomalies was 433.5/10,000 livebirths. When compared with the prevalence of each major anomaly in EUROCAT, the prevalence of spina bifida, atrial septal defect (ASD), congenital megacolon, hip dislocation and/or dysplasia and skeletal dysplasia were more than five times higher in Korea. In contrast, the prevalence of aortic atresia/interrupted aortic arch and gastroschisis was less than one-fifth in Korea. The proportion of preterm births was 15.7%; however, more than 40% of infants with anencephaly, annular pancreas and gastroschisis were preterm infants. Additionally, 29.2% of the major anomalies were admitted to the neonatal intensive care units at birth, and 25.6% received surgical operation. The mortality rate was 1.7%, and 78.2% of the deaths occurred within the first year of life. However, in neonates with tricuspid valve atresia and stenosis, duodenal atresia or stenosis, and diaphragmatic hernia, more than half died within their first month of life. ASD and ventricular septal defect were the most common anomalies, and trisomy 18 and hypoplastic left heart syndrome were the most fatal anomalies. All infants with aortic atresia/interrupted aortic arch and conjoined twins received surgery. CONCLUSION: The proportion of surgeries, preterm births and mortality was high in infants with major congenital anomalies. The establishment of a national registry of congenital anomalies and systematic support by national medical policies are needed for infants with major congenital anomalies in Korea. | F33: J Korean Med Sci | G33: Journal Article | H33: A | I33: Incluir | J33: A | M33: Verificar no texto completo se há dado específico e separável da T18 | N33: =HYPERLINK("https://pubmed.ncbi.nlm.nih.gov/37821084/","abrir") -> abrir | O33: =IF(B33 < 2024, FALSE() , TRUE()) -> FALSE
A34: 38047023 | B34: 2023 | C34: Koshida S | D34: Significant improvement in survival outcomes of trisomy 18 with neonatal intensive care compared to non-intensive care: a single-center study. | E34: BACKGROUND: Trisomy 18 syndrome, also known as Edwards syndrome, is a chromosomal trisomy. The syndrome has historically been considered lethal owing to its poor prognosis, and palliative care was primarily indicated for trisomy 18 neonates. Although there have been several reports on the improvement of survival outcomes in infants with trisomy 18 syndrome through neonatal intensive care, few studies have compared the impact of neonatal intensive care on survival outcomes with that of non-intensive care. Therefore, we compared the survival-related outcomes of neonates with trisomy 18 between intensive and non-intensive care. METHODS: Seventeen infants of trisomy 18 admitted to our center between 2007 and 2019 were retrospectively studied. We divided the patients into a non-intensive group (n = 5) and an intensive group (n = 12) and evaluated their perinatal background and survival-related outcomes of the two groups. RESULTS: The 1- and 3-year survival rates were both 33% in the intensive group, which was significantly higher than that in the non-intensive group (p < 0.001). Half of the infants in the intensive care group were discharged alive, whereas in the non-intensive care group, all died during hospitalization (p = 0.049). CONCLUSIONS: Neonatal intensive care for neonates with 18 trisomy significantly improved not only survival rates but also survival-discharge rates. Our findings would be helpful in providing 18 trisomy neonates with standard neonatal intensive care when discussing medical care with their parents. | F34: PeerJ | G34: Journal Article; Research Support, Non-U.S. Gov't | H34: A | I34: Incluir | J34: A | N34: =HYPERLINK("https://pubmed.ncbi.nlm.nih.gov/38047023/","abrir") -> abrir | O34: =IF(B34 < 2024, FALSE() , TRUE()) -> FALSE
A35: 38075989 | B35: 2023 | C35: Çelik M | D35: Effect of cardiac surgery on survival in patients with trisomy 18: A single-center experience. | E35: BACKGROUND: In this study, we aimed to compare the results of operated patients diagnosed with trisomy 18 with those who were followed with medical treatment alone. METHODS: Between May 2014 and January 2022, a total of 18 patients (6 males, 12 females; median age: 39 days; range, 32 to 79 days) diagnosed with trisomy 18 were retrospectively analyzed. Patient data were obtained from the pediatric cardiovascular surgery digital database. The patients were divided into two groups: those who underwent surgery (n=10) and those who were followed with medical treatment (n=8). RESULTS: Cardiac pathology was detected in all 18 patients included in the study. Three (30%) patients in the surgical group and two (25%) patients in the medical treatment group were discharged and followed with medical treatment. One of the three patients discharged after surgery died during follow-up. The median survival in surgical and medical treatment groups was 150 (range, 75 to 308) days and eight (range, 3 to 51) days, respectively (p=0.009). While patients in the medical treatment group died due to multi-organ failure, those in surgical group died due to sepsis, heart failure, and respiratory failure. CONCLUSION: Although cardiac surgery contributed positively to survival in patients with trisomy 18, the mortality rate was still high due to non-cardiac causes. We believe that a multidisciplinary approach would contribute positively to the treatment of this patient group with multi-organ failure and would aid in prolonging their life span. | F35: Turk Gogus Kalp Damar Cerrahisi Derg | G35: Journal Article | H35: A | I35: Incluir | J35: A | N35: =HYPERLINK("https://pubmed.ncbi.nlm.nih.gov/38075989/","abrir") -> abrir | O35: =IF(B35 < 2024, FALSE() , TRUE()) -> FALSE
A36: 38088680 | B36: 2023 | C36: Marçola L | D36: Patau and Edwards Syndromes in a University Hospital: beyond palliative care. | E36: OBJECTIVE: To describe the newborn population with Patau (T13) and Edwards Syndrome (T18) with congenital heart diseases that stayed in the Intensive Care Unit (ICU) of a quaternary care hospital complex, regarding surgical and non-surgical medical procedures, palliative care, and outcomes. METHODS: Descriptive case series conducted from January/2014 to December/2018 through analysis of records of patients with positive karyotype for T13 or T18 who stayed in the ICU of a quaternary hospital. Descriptive statistics analysis was applied. RESULTS: 33 records of eligible patients were identified: 27 with T18 (82%), and 6 T13 (18%); 64% female and 36% male. Eight were preterm infants with gestational age between 30-36 weeks (24%), and only 4 among the 33 infants had a birth weight >2500 g (12%). Four patients underwent heart surgery and one of them died. Intrahospital mortality was 83% for T13, and 59% for T18. The majority had other malformations and underwent other surgical procedures. Palliative care was offered to 54% of the patients. The median hospitalization time for T18 and T13 was 29 days (range: 2-304) and 25 days (13-58), respectively. CONCLUSIONS: Patients with T13 and T18 have high morbidity and mortality, and long hospital and ICU stays. Multicentric studies are needed to allow the analysis of important aspects for creating protocols that, seeking therapeutic proportionality, may bring better quality of life for patients and their families. | F36: Rev Paul Pediatr | G36: Journal Article | H36: A | I36: Incluir | J36: A | M36: Verificar o país (possivelmente Brasil). | N36: =HYPERLINK("https://pubmed.ncbi.nlm.nih.gov/38088680/","abrir") -> abrir | O36: =IF(B36 < 2024, FALSE() , TRUE()) -> FALSE
A37: 34889030 | B37: 2022 | C37: Tamaki S | D37: Improving survival in patients with trisomy 18. | E37: The effects of medical and surgical interventions on the survival of patients with trisomy 18 have been reported, leading to changes in perinatal management and decision-making. However, few studies have fully reported the recent changes in survival and treatment of trisomy 18. We examined how treatment and survival of patients with trisomy 18 have changed over a decade in a Japanese pediatric tertiary referral center. This retrospective cohort study included patients with trisomy 18 who were admitted within the first 7 days of life at the Hyogo Prefectural Kobe Children's Hospital between 2008 and 2017. The patients were divided into early period (EP) and late period (LP) groups based on the birth year of 2008-2012 and 2013-2017, respectively. Changes in treatment and survival rates were compared between the two groups. A total of 56 patients were studied (29 in the EP group and 27 in the LP group). One-year survival rates were 34.5% and 59.3% in the EP and LP groups, respectively. The survival to discharge rate significantly increased from 27.6% in the EP group to 81.5% in the LP group (p < 0.001). The proportion of patients receiving surgery, especially for congenital heart defects, significantly increased from 59% in the EP group to 96% in the LP group (p = 0.001). In our single-center study, survival and survival to discharge were significantly improved in patients with trisomy 18, probably because of increased rate of surgical interventions. These findings may facilitate better decision-making by patients' families and healthcare providers. | F37: Am J Med Genet A | G37: Journal Article | H37: A | I37: Incluir | J37: A | N37: =HYPERLINK("https://pubmed.ncbi.nlm.nih.gov/34889030/","abrir") -> abrir | O37: =IF(B37 < 2024, FALSE() , TRUE()) -> FALSE
A38: 35156266 | B38: 2022 | C38: Matthews LJ | D38: Morbidity and mortality following noncardiac surgical procedures among children with autosomal trisomy. | E38: BACKGROUND: Trisomy 13 (T13), trisomy 18 (T18), and trisomy 21 (T21) are the most common autosomal trisomies. One unifying feature of all trisomies is their association with major congenital malformations, which often require life-prolonging surgical procedures. Few studies, mostly among cardiac surgery patients, have examined the outcome of those who undergo surgical procedures. We examined the differences in postsurgical outcomes between the trisomy groups. METHOD: Using the National Surgical Quality Improvement Program dataset, we identified children (<18 years of age) with T13, T18, or T21 who underwent noncardiac surgery (2012-2018). We estimated the incidence of mortality and indicator of resource utilization (unplanned reoperation, unplanned tracheal reintubation, and extended length of hospital stay). RESULTS: Of the 349 158 inpatient surgical cases during the study period, we identified 4202 children with one of the autosomal trisomies of interest (T13: 152; T18: 335; and T21: 3715). The rates of postoperative mortality were substantially higher for T18 and T13 than T21 and nontrisomy children (T18 vs. T21: 11.1% vs. 1.6%, adjusted odds ratio: 5.01, 95%CI: 2.89,8.70, p < .01), (T13 vs. T21: 8.1% vs. 1.6%, adjusted odds ratio: 2.86, 95%CI: 1.25,6.54, p = .01). Children with T18 had the highest rates of extended length of stay (62.7%) and prolonged mechanical ventilation (32.5%). T18 and T13 neonates had the highest surgical mortality burden (T13: 26.5%, T18: 31.8%, and T21: 2.8%). CONCLUSION: Approximately, one-third of T18 and T13 neonates, who had surgery, died, underscoring the lethality of these trisomies and the need for a comprehensive preoperative ethical discussion with families of these children. | F38: Paediatr Anaesth | G38: Journal Article | H38: A | I38: Incluir | J38: A | N38: =HYPERLINK("https://pubmed.ncbi.nlm.nih.gov/35156266/","abrir") -> abrir | O38: =IF(B38 < 2024, FALSE() , TRUE()) -> FALSE
A39: 35452657 | B39: 2022 | C39: Cortezzo DE | D39: Perinatal Outcomes of Fetuses and Infants Diagnosed with Trisomy 13 or Trisomy 18. | E39: OBJECTIVES: To identify factors associated with prenatal, perinatal, and postnatal outcomes, and determine medical care use for fetuses and infants with trisomy 13 (T13) and trisomy 18 (T18). STUDY DESIGN: This population-based retrospective cohort study included all prenatal and postnatal diagnoses of T13 or T18 in the greater Cincinnati area from January 1, 2012, to December 31, 2018. Overall survival, survival to hospital discharge, medical management, and maternal, fetal, and neonatal characteristics are analyzed. RESULTS: There were 124 pregnancies (125 fetuses) that were identified, which resulted in 72 liveborn infants. Male fetal sex and hydrops were associated with a higher rate of spontaneous loss. The median length of survival was 7 and 29 days, for infants with T13 and T18, respectively. Of the 27 infants alive at 1 month of age, 13 (48%) were alive at 1 year of age. Only trisomy type (T13), goals of care (comfort care), and extremely low birthweight were associated with a shorter length of survival. A high degree of variability existed in the use of medical services, with 28% of infants undergoing at least 1 surgical procedure and some children requiring repeated (≤29) or prolonged (>1 year) hospitalizations. CONCLUSIONS: Although many infants with T13 or T18 did not survive past the first week of life, nearly 20% lived for more than 1 year with varying degrees of medical support. The length of survival for an infant cannot be easily predicted, and surviving infants have high health care use throughout their lifespans. | F39: J Pediatr | G39: Journal Article | H39: A+B | I39: Incluir | J39: A+B | N39: =HYPERLINK("https://pubmed.ncbi.nlm.nih.gov/35452657/","abrir") -> abrir | O39: =IF(B39 < 2024, FALSE() , TRUE()) -> FALSE
A40: 35522316 | B40: 2022 | C40: Silva C | D40: Trisomy 18-when the diagnosis is compatible with life. | E40: UNLABELLED: Trisomy 18 is an autosomal chromosomal disorder characterized by the presence of an extra 18 chromosome. In the last decades, and as novel therapeutic options emerged, a paradigm shift on the treatments available to these children occurred, establishing the need to deepen the knowledge regarding the management/treatment of children diagnosed with trisomy 18. This retrospective cohort study sought to characterize the clinical path and survival of the children with the diagnosis of trisomy 18 followed in a tertiary pediatric hospital between 1995 and 2020. Medical records were reviewed, and epidemiological and clinical features and follow-up data were collected. Six patients were identified, two with mosaicism (33.3%) and four were female (66.7%). All had cardiovascular, cognitive, and physical development anomalies or minor congenital anomalies. Most presented neurological anomalies (n = 4, 66.7%) and feeding difficulties (n = 4, 66.7%). Four children (66.7%) required medical devices or equipment and all required chronic medication. Two children (33.3%) underwent surgical interventions. Four children (66.7%) were hospitalized in the last year of life. Three patients had a do not resuscitate order (50%) but only one child was referred to a pediatric palliative care team (16.7%). One-month, 1-year, and 10-year survival were 66.7% (n = 4), 33.3% (n = 2, both with mosaicism), and 16.7% (n = 1, with mosaicism) respectively. CONCLUSIONS: Knowledge of the multiple comorbidities and complex care needs of children with this syndrome is crucial. Every-day care and decisions about invasive treatments may raise ethical issues. Early referral to pediatric palliative care teams is essential to promote a holistic advanced care plan for both the patient and his family. WHAT IS KNOWN: • The increase in survival and the high morbimortality that trisomy 18 still entails demands a careful deliberation on the use of invasive treatment. WHAT IS NEW: • Recent studies show that the labels of "incompatible with life"/"lethal" are not adequate, establishing a need to change this mindset. • The development of pediatric palliative care teams in the last decade and early referral allow for an optimal individualized advanced care plan. Under-referral to pediatric palliative care teams persists and efforts must be made to increase awareness of their existence and role in patient care. | F40: Eur J Pediatr | G40: Journal Article | H40: A | I40: Incluir | J40: A | M40: Inclui mosaicos (2 de 6): analisar separadamente. | N40: =HYPERLINK("https://pubmed.ncbi.nlm.nih.gov/35522316/","abrir") -> abrir | O40: =IF(B40 < 2024, FALSE() , TRUE()) -> FALSE
A41: 36013402 | B41: 2022 | C41: Springer S | D41: Outcome after Prenatal Diagnosis of Trisomy 13, 18, and 21 in Fetuses with Congenital Heart Disease. | E41: Fetal congenital heart disease (CHD) is often associated with chromosomal abnormalities. Our primary aim was to assess stillbirth and neonatal mortality rates for pregnancies complicated by trisomies 13, 18, and 21 in the presence of CHD, from a single tertiary referral center during 2000-2020 in a retrospective cohort study. The secondary aims were to investigate maternal morbidity in these pregnancies, and to study the gestational or neonatal age when mortality occurred. Inclusion criteria were the prenatal diagnosis of at least one structural CHD, together with prenatally diagnosed fetal trisomy 13, 18, or 21. One-hundred and sixty patients with fetal trisomy 13 (14.4%), fetal trisomy 18 (28.8%), and fetal trisomy 21 (56.9%) were evaluated. In total, 98 (61.3%) families opted for the termination of pregnancy (TOP). Of the remaining 62 (38.8%) pregnancies, 16 (25.8%) resulted in intrauterine fetal death/death during delivery. Ten out of twenty-one (47.6%) infants with trisomy 13 or 18 were born alive. The livebirth rate was 87.8% (36/41) for infants with trisomy 21. Early neonatal death was observed in nine (19.6%) infants. Thirty-one (86.1%) infants with trisomy 21 survived the first year of life. These data may be helpful for counseling affected parents when the decision to terminate or continue the pregnancy should be considered. | F41: Life (Basel) | G41: Journal Article | H41: A+B | I41: Incluir | J41: A+B | N41: =HYPERLINK("https://pubmed.ncbi.nlm.nih.gov/36013402/","abrir") -> abrir | O41: =IF(B41 < 2024, FALSE() , TRUE()) -> FALSE
A42: 36403096 | B42: 2022 | C42: Stewart C | D42: Survival rates and outcomes of pregnancies with prenatal diagnosis of trisomy 18: A 16-year experience from a public hospital in South Africa. | E42: OBJECTIVE: Many studies, largely from high-income countries (HIC), have reported outcomes in babies with trisomy 18 (T18), with a paucity of data from Africa. Knowledge of outcomes is important in counselling women prenatally diagnosed with T18. We aimed to review all prenatally diagnosed cases of T18 between January 2006 and December 2021. METHOD: Demographic data, diagnosis, gestation and outcome data were obtained from the Astraia® database and patient files. RESULTS: We included 88 pregnant women of whom 46 terminated their pregnancies (30 beyond 24 weeks' gestation). Three underwent foeticides, one had a caesarean section for maternal obstetric reasons and 26 underwent inductions of labour without foetal monitoring. Four neonates were live born but none lived >8 h. In those who continued their pregnancies, the mean gestation at delivery was 34.8 weeks, 14 (33%) were live births and only 5 survived for >24 h with none surviving to 1 year of life. CONCLUSION: In our cohort, infants with T18 had lower live birth rates and shorter survival than in the current literature from HIC. This may be due to the implementation of non-aggressive intrapartum care and comfort care for the neonates. This has implications for counselling in our setting. | F42: Prenat Diagn | G42: Journal Article | H42: A+B | I42: Incluir | J42: A+B | M42: África do Sul: diagnóstico pré-natal, sem sobreviventes a 1 ano. | N42: =HYPERLINK("https://pubmed.ncbi.nlm.nih.gov/36403096/","abrir") -> abrir | O42: =IF(B42 < 2024, FALSE() , TRUE()) -> FALSE
A43: 36590710 | B43: 2022 | C43: Rosenblum JM | D43: Cardiac surgery in children with trisomy 13 or trisomy 18: How safe is it? | E43: OBJECTIVE: Surgery for heart defects in children with trisomy 13 or 18 is controversial. We analyzed our 20-year experience. METHODS: Since 2002, we performed 21 operations in 19 children with trisomy 13 (n = 8) or trisomy 18 (n = 11). Age at operation was 4 days to 12 years (median, 154 days). Principal diagnosis was ventricular septal defect in 10 patients, tetralogy of Fallot in 7 patients, arch hypoplasia in 1 patient, and patent ductus arteriosus in 1 patient. RESULTS: The initial operation was ventricular septal defect closure in 9 patients, tetralogy of Fallot repair in 7 patients, pulmonary artery banding in 1 patient, patent ductus arteriosus ligation in 1 patient, and aortic arch/coarctation repair in 1 patient. There were no operative or hospital deaths. Median postoperative intensive care and hospital stays were 189 hours (interquartile range, 70-548) and 14 days (interquartile range, 8.0-37.0), respectively, compared with median hospital stays in our center for ventricular septal defect repair of 4.0 days and tetralogy of Fallot repair of 5.0 days. On median follow-up of 17.4 months (interquartile range, 6.0-68), 1 patient was lost to follow-up after 5 months. Two patients had reoperation without mortality. There have been 5 late deaths (4 with trisomy 18, 1 with trisomy 13) predominately due to respiratory failure from 4 months to 9.4 years postoperatively. Five-year survival was 66.6% compared with 24% in a group of unoperated patients with trisomy 13 or 18. CONCLUSIONS: Cardiac operation with an emphasis on complete repair can be performed safely in carefully selected children with trisomy 13 or trisomy 18. Hospital resource use measured by postoperative intensive care and hospital stays is considerably greater compared with nontrisomy 13 and 18. | F43: JTCVS Open | G43: Journal Article | H43: A | I43: Incluir | J43: A | N43: =HYPERLINK("https://pubmed.ncbi.nlm.nih.gov/36590710/","abrir") -> abrir | O43: =IF(B43 < 2024, FALSE() , TRUE()) -> FALSE
A44: 32646662 | B44: 2021 | C44: Bajinting A | D44: To operate or not to operate? Assessing NSQIP surgical outcomes in trisomy 18 patients. | E44: BACKGROUND: Trisomy 18 is associated with a wide range of potentially fatal congenital conditions. Historically, clinical attitudes on treatment have been ambiguous, with palliative care as the standard of care. The aim of our study was to provide a descriptive analysis of surgical outcomes in patients with trisomy 18. STUDY DESIGN: We identified patients with trisomy 18 aged 0-18 years using the NSQIP-Pediatric database from 2012 to 2017 and analyzed demographics, surgery types, and perioperative characteristics of patients with trisomy 18 patients undergoing surgical intervention. Additionally, a case-match analysis was performed to assess surgical outcome differences. RESULTS: A total of 310 patients with trisomy 18 were identified. Thirty-one percent were >5 years of age and 73% were female. The most common surgical types were general surgery procedures (57.4%), followed by orthopedics (18.1%) and ENT (10.3%). Operations performed increased from 8% (2012) to 26% (2017), and only 23% of patients had previous cardiac surgery. Majority of patients had no prior history of malignancy (95%) and 5% had a tracheostomy placed. Discharge to home was achieved in 74% of patients, with a median total hospital length of stay of 5 days (IQR 17). Furthermore, 90% survived over 30 days from the operation. Thirty-two patients had readmissions and the most common reasons were dehydration, gastrostomy infection or malfunction. Surgical site infections occurred in <3% of patients. No differences in complications, length of stay, reoperations, and readmissions were identified by case-match analysis. CONCLUSION: In this data set, patients with trisomy 18 undergoing noncardiac surgical procedures experience excellent surgical outcomes with minimal morbidity and low mortality. Most patients more than a year of age will experience similar outcomes to patients without trisomy 18. TYPE OF STUDY: Treatment study (retrospective comparative study) LEVEL OF EVIDENCE: Level III. | F44: J Pediatr Surg | G44: Journal Article | H44: A | I44: Incluir | J44: A | N44: =HYPERLINK("https://pubmed.ncbi.nlm.nih.gov/32646662/","abrir") -> abrir | O44: =IF(B44 < 2024, FALSE() , TRUE()) -> FALSE
A45: 32862054 | B45: 2021 | C45: Alore EA | D45: Outcomes After Extracorporeal Life Support Cannulation in Pediatric Patients With Trisomy 13 and Trisomy 18. | E45: BACKGROUND: Indications for extracorporeal life support (ECLS) have evolved and expanded, yet its use in trisomy 13 (T13) and trisomy 18 (T18) patients remains controversial. We reviewed the experience of the Extracorporeal Life Support Organization with ECLS in these patients to inform practice at our institution. METHODS: The Extracorporeal Life Support Organization registry was queried for all patients younger than 18 y with an International Classification of Diseases, Ninth Edition/Tenth Edition code for T13 or T18 from 2000 to 2018. Basic demographics, ECLS details, and clinical outcomes were recorded. Descriptive statistics were performed. RESULTS: Twenty-eight patients were identified (15 with T13; 13 with T18), representing 0.06% (28 of 46,901) of pediatric ECLS cannulations. The median weight was 3.5 kg (range, 1.4-13), and age at cannulation was 52 d (range, 0 d-6.8 y). Time on ECLS ranged from 13 to 478 h (median, 114). Cardiac defects were diagnosed in 19 (68%) patients, of which 13 (46%) underwent surgical repair. Median oxygenation index pre-ECLS was 45. Venoarterial cannulations accounted for 82% of patients, whereas 14% underwent venovenous cannulation. Overall survival to hospital discharge was 46% with 86% of patients experiencing one or more complications. There were no survivors when cannulation continued past 12 d. CONCLUSIONS: Although complications are frequent, the mortality rate in patients with T13 and T18 remains within the reported range for the general pediatric population. T13 and T18 alone should not be viewed as absolute contraindications to ECLS within the pediatric population but rather considered during the evaluation of a patient's potential candidacy. | F45: J Surg Res | G45: Evaluation Study; Journal Article | H45: A | I45: Incluir | J45: A | N45: =HYPERLINK("https://pubmed.ncbi.nlm.nih.gov/32862054/","abrir") -> abrir | O45: =IF(B45 < 2024, FALSE() , TRUE()) -> FALSE
A46: 32943740 | B46: 2021 | C46: Kawasaki H | D46: The short-term mortality and morbidity of very low birth weight infants with trisomy 18 or trisomy 13 in Japan. | E46: Trisomy 18 (T18) and trisomy 13 (T13) are major concerns in prenatal genetic testing due to their poor prognosis; very low birth weight (VLBW) is also a concern in neonatology. The aim of this study was to investigate the mortality and morbidity of VLBW infants diagnosed with T18/T13 in Japan, compared with those with no birth defects (BD-). Maternal and neonatal data were collected prospectively from infants weighing <1501 g and were admitted to centers of the Neonatal Research Network of Japan during 2003 to 2016. Among 60,136 infants, 563 and 60 was diagnosed with T18 and T13, respectively. Although the age of mothers of infants with T18/T13 was higher, the frequency of maternal complications was lower than those with BD-. With maternal and neonatal characteristic adjustments, T18/T13 had a higher incidence of each morbidity when compared with BD-. Mortality rates in the NICU were 70, 77, and 5.8% for T18, T13, and BD-, respectively, while the survival discharge rates of T18 and T13 were 29.5 and 23.3%, respectively, which was significantly higher than previous reports. This was the first nationwide survey for VLBW infants with T18/T13 in Japan; this novel data will be relevant and useful for prenatal genetic counseling and perinatal management. Although T18/T13 were considered to be fatal in the past, with proper epidemiological information, discussions with affected families, and compassionate patient care, the mortality rate of T18/T13 can be improved. | F46: J Hum Genet | G46: Journal Article | H46: A | I46: Incluir | J46: A | N46: =HYPERLINK("https://pubmed.ncbi.nlm.nih.gov/32943740/","abrir") -> abrir | O46: =IF(B46 < 2024, FALSE() , TRUE()) -> FALSE
A47: 33403783 | B47: 2021 | C47: Kosiv KA | D47: A validated model for prediction of survival to 6 months in patients with trisomy 13 and 18. | E47: Congenital heart disease is exceedingly prevalent in trisomy 13 and 18. Improved survival following congenital heart surgery has been reported, however, mortality remains significantly elevated. Utilizing inpatient data on trisomy 13 and 18 from the 2003-2016 Pediatric Health Information System database, a survival model was developed and validated using data from the California Perinatal Quality Care Collaborative and the California Office of Statewide Health Planning and Development. The study cohort included 1,761 infants with trisomy 13 and 18. Two models predicting survival to 6 months of age were developed and tested. The initial model performed excellently, with a c-statistic of 0.87 and a c-statistic of 0.76 in the validation cohort. After excluding procedures performed on the day of death, the revised model's c-statistic was 0.76. Certain variables, including cardiac surgery, gastrostomy, parenteral nutrition, and mechanical ventilation, are predictive of survival to 6 months of age. This study presents a model, which potentially can inform decision-making regarding congenital heart surgery. | F47: Am J Med Genet A | G47: Journal Article; Multicenter Study; Validation Study | H47: A | I47: Incluir | J47: A | N47: =HYPERLINK("https://pubmed.ncbi.nlm.nih.gov/33403783/","abrir") -> abrir | O47: =IF(B47 < 2024, FALSE() , TRUE()) -> FALSE
A48: 33486488 | B48: 2021 | C48: Suto M | D48: Population-Based Analysis of Secular Trends in Age at Death in Trisomy 18 Syndrome in Japan from 1975 to 2016. | E48: INTRODUCTION: Despite changes in prenatal diagnostic methods and perceptions regarding the prognosis of and treatment options for patients with trisomy 18 syndrome, data on the secular changes in patient survival are limited. This study aimed to investigate the survival pattern for such patients. METHODS: To investigate the general patient survival patterns, we used data from the vital statistics database of deaths in Japan from 1975 to 2016. We described demographic factors, such as sex, gestational age at delivery, and surgical history, for patients whose primary cause of death was trisomy 18 syndrome. RESULTS: The proportions of deaths within 24 h of birth (4.0% in 1975-1980 to 21.9% in 2011-2016) and at age ≥1 year (8.9% in 1975-1980 to 17.7% in 2011-2016) increased. The median survival time was higher for females, infants born after 37 weeks of gestation, and those who received surgical intervention. The median survival time tripled among patients who received surgical intervention (61.5 days in 1995-2005 to 182.5 days in 2006-2016), and the proportion of such patients increased (from 3.8% in 1995 to 24.1% of the entire affected population in 2016). DISCUSSION/CONCLUSION: In Japan, the median survival time of infants with trisomy 18 increased over time, and the proportion of death within 24 h and at ≥1 year increased. Greater acknowledgement of the possible benefits of surgical intervention likely led to the increased provision of interventions and contributed to the increased survival time. | F48: Neonatology | G48: Journal Article; Research Support, Non-U.S. Gov't | H48: A | I48: Incluir | J48: A | M48: Base populacional (Japão, 1975–2016). | N48: =HYPERLINK("https://pubmed.ncbi.nlm.nih.gov/33486488/","abrir") -> abrir | O48: =IF(B48 < 2024, FALSE() , TRUE()) -> FALSE
A49: 33515091 | B49: 2021 | C49: Nakai R | D49: Survival Outcomes of Two-Stage Intracardiac Repair in Large Ventricular Septal Defect and Trisomy 18. | E49: BACKGROUND: Surgical management has not been encouraged in patients with trisomy 18 (T18) and congenital heart diseases due to poor survival. This study aimed to investigate (1) the appropriateness of palliative surgeries followed by intracardiac repair (ICR) (i.e., two-stage ICR) for patients with a large ventricular septal defect (VSD) and T18, and (2) its impact on their long-term outcomes. METHODS: Medical charts of patients with VSD and T18 who underwent two-stage ICR at the Japanese Red Cross Medical Center between January 2005 and December 2019 were retrospectively reviewed. Demographic data, timing, and types of palliative surgeries, information related to ICR, peri- and postoperative clinical information, postoperative survival, and cause of death were collected. The long-term prognosis of patients treated with two-stage ICR was compared with that of patients treated with primary ICR and palliative surgery without ICR. RESULTS: Overall, 18 (2 male, 16 female) patients underwent two-stage ICR. Pulmonary artery banding was the initial palliative surgery in all patients after a median duration of 19.5 (range 6-194) days of life. The median age and the mean body weight at the time of ICR were 18.2 (7.6-50.7) months and 6.0 ± 1.0 kg, respectively. The mean pulmonary artery pressure and pulmonary vascular resistance index before ICR were 19.1 ± 7.3 mmHg and 3.4 ± 2.0 U m2, respectively. Overall, 17/18 (94%) patients were discharged after ICR. Fourteen (78%) patients were alive during data collection. None of the patients died of cardiac insufficiency, and the median duration of survival was 46.3 (14.3-186.4) months since birth. Most patients required cardiac medications rather than pulmonary vasodilators at the last follow-up. During the study period, three patients underwent primary ICR, and 46 underwent palliative surgery without ICR. Of those who underwent primary ICR, two died in the hospital on the first and 48th day following ICR, and the third died 179 days after the ICR. The Log-rank test revealed a significantly longer survival for the patients treated with two-stage ICR compared with those treated with palliative surgery without ICR (P = 0.003). CONCLUSION: Two-stage ICR improves the long-term survival of patients with VSDs and T18. This safe surgical strategy can also prevent pulmonary hypertension in such patients. | F49: Pediatr Cardiol | G49: Journal Article | H49: A | I49: Incluir | J49: A | N49: =HYPERLINK("https://pubmed.ncbi.nlm.nih.gov/33515091/","abrir") -> abrir | O49: =IF(B49 < 2024, FALSE() , TRUE()) -> FALSE
A50: 34112961 | B50: 2021 | C50: Acharya K | D50: Medical and surgical interventions and outcomes for infants with trisomy 18 (T18) or trisomy 13 (T13) at children's hospitals neonatal intensive care units (NICUs). | E50: OBJECTIVES: To examine characteristics and outcomes of T18 and T13 infants receiving intensive surgical and medical treatment compared to those receiving non-intensive treatment in NICUs. STUDY DESIGN: Retrospective cohort of infants in the Children's Hospitals National Consortium (CHNC) from 2010 to 2016 categorized into three groups by treatment received: surgical, intensive medical, or non-intensive. RESULTS: Among 467 infants admitted, 62% received intensive medical treatment; 27% received surgical treatment. The most common surgery was a gastrostomy tube. Survival in infants who received surgeries was 51%; intensive medical treatment was 30%, and non-intensive treatment was 72%. Infants receiving surgeries spent more time in the NICU and were more likely to receive oxygen and feeding support at discharge. CONCLUSIONS: Infants with T13 or T18 at CHNC NICUs represent a select group for whom parents may have desired more intensive treatment. Survival to NICU discharge was possible, and surviving infants had a longer hospital stay and needed more discharge supports. | F50: J Perinatol | G50: Journal Article | H50: A | I50: Incluir | J50: A | N50: =HYPERLINK("https://pubmed.ncbi.nlm.nih.gov/34112961/","abrir") -> abrir | O50: =IF(B50 < 2024, FALSE() , TRUE()) -> FALSE
A51: 34215991 | B51: 2021 | C51: Gunne E | D51: Fatal fetal abnormality Irish live-born survival-an observational study. | E51: The aim of the study was to provide accurate information regarding live-born infant survival after diagnosis of fatal fetal anomaly (FFA) to aid decision-making in respect of pregnancy management, and to ascertain the natural history of live-born infants with FFAs via a retrospective analysis of death records (2006-2018), from the National Paediatric Mortality Registry (source Central Statistics Office 2019). Diagnoses and survival times were ascertained from narrative records with further ascertainment and reconciliation of trisomies 13 and 18 cases by review of cytogenetic test records, the National Death Events Register and National Perinatal Epidemiology Centre data. During the study period, termination of pregnancy was not permitted under the Irish Constitution. Patients are live-born babies with fatal fetal anomalies whose deaths were registered in the Republic of Ireland. The main outcome measure was construction of anomaly-specific survival curves, or survival time range and median for those anomalies with rare occurrence. Survival curves for anencephaly, bilateral renal agenesis, thanatophoric dysplasia, trisomy 13, and trisomy 18 show that 90% (n = 95), 93% (n = 60), 100% (n = 14), 37% (n = 92) and 33% (n = 162), respectively, were deceased by 24 h and 98%, 100%, 100%, 73%, and 53%, respectively, by 1 week post-delivery. Survival time range and median were calculated for triploidy (3.5 h-20 days; 10.5 days), whose occurrence was rare. Anhydramnios, craniorachischisis, hydranencephaly and severe hydrocephalus were extremely rare and all deaths were neonatal deaths. Our results provide 13 years of national natural history data of live birth FFA survival. This provides objective information to aid obstetric counselling of couples upon diagnosis of an FFA. | F51: J Community Genet | G51: Journal Article | H51: A | I51: Incluir | J51: A | M51: Destaque: Irlanda, categoria legal "fatal fetal anomaly", período em que o aborto não era permitido (direito comparado). | N51: =HYPERLINK("https://pubmed.ncbi.nlm.nih.gov/34215991/","abrir") -> abrir | O51: =IF(B51 < 2024, FALSE() , TRUE()) -> FALSE
A52: 34363815 | B52: 2021 | C52: Fick TA | D52: Trisomy 18 Trends over the Last 20 Years. | E52: OBJECTIVE: To evaluate the trends in hospitalizations for children with trisomy 18 over time and to determine the rate of invasive procedures on these children, using a large inpatient database. STUDY DESIGN: A retrospective analysis using the Kids' Inpatient Database from 1997 to 2016 was performed for trisomy 18. We evaluated survival to discharge as well as the presence of pulmonary, skeletal, neurologic, gastrointestinal, renal, and hematologic/bleeding problems. We also searched for the following interventions, if performed: gastrostomy tube placement, tracheostomy, or cardiac procedure. RESULTS: Over this period 10 151 admissions occurred in children with a diagnosis of trisomy 18. Between 1997 and 2016, the number of children admitted annually with trisomy 18 increased 74% from 1036 to 1798. The proportion of patients born prematurely remained stable at 14%-16% throughout the study. Gastrostomy tube placement increased 12-fold during the study period, tracheostomy increased 11-fold, and cardiac intervention increased 5-fold. The overall mortality rate decreased in those with trisomy 18 from 32% in 1997 to 21% in 2016. CONCLUSIONS: We highlight a decreased inpatient mortality rate during the study period. The number of children undergoing interventions such as gastrostomy tube and tracheostomy increased, as did the number of children undergoing cardiac intervention. Although the number of procedures has increased with the mortality rate decreasing, it is unclear at present whether the 2 are related. | F52: J Pediatr | G52: Journal Article | H52: A | I52: Incluir | J52: A | M52: Tendências de 20 anos (Fick). | N52: =HYPERLINK("https://pubmed.ncbi.nlm.nih.gov/34363815/","abrir") -> abrir | O52: =IF(B52 < 2024, FALSE() , TRUE()) -> FALSE
A53: 34415101 | B53: 2021 | C53: Inoue H | D53: Survival outcomes of very low birth weight infants with trisomy 18. | E53: Trisomy 18 (T18) is one of the most commonly diagnosed aneuploidies leading to poor survival outcome. However, little is known about the dual risk of T18 and very low birth weight (VLBW, weighing <1500 g at birth). We aimed to investigate the survival and clinical features of VLBW infants with T18. In this observational cohort study, infants with T18 admitted to the neonatal intensive care unit in Kyushu University Hospital from 2000 to 2019 were eligible. Among 30 infants with T18 who were enrolled as study participants, 11 (37%) were born with VLBW. VLBW infants had lower gestational age (34.4 vs. 39.4 weeks, p < 0.01) and a higher incidence of esophageal atresia (64% vs. 11%, p < 0.01) than non-VLBW infants. The proportions of patients who underwent any surgery (55% vs. 5%, p < 0.01) and positive pressure ventilation (82% vs. 32%, p = 0.02) were higher in VLBW than non-VLBW infants. One-year overall survival rate (45% vs. 26%, p = 0.32 by log-rank test) did not differ between the two groups. In conclusion, being born at VLBW may not be fatal for infants with T18 undergoing active interventions. | F53: Am J Med Genet A | G53: Journal Article; Research Support, Non-U.S. Gov't | H53: A | I53: Incluir | J53: A | N53: =HYPERLINK("https://pubmed.ncbi.nlm.nih.gov/34415101/","abrir") -> abrir | O53: =IF(B53 < 2024, FALSE() , TRUE()) -> FALSE
A54: 31763690 | B54: 2020 | C54: Taira R | D54: Management of apnea in infants with trisomy 18. | E54: This case series aimed to characterize the clinical features, management, and outcomes of apnea in infants with trisomy 18. Participants in this study were infants with trisomy 18 who were born alive and admitted to the neonatal intensive care unit in Kyushu University Hospital from 2000 to 2018. Retrospective analysis was performed on clinical data recorded in our department. Twenty-seven infants with trisomy 18 were admitted to our hospital during the study period, of which 25 (nine males, 16 females) were enrolled as eligible participants in this study. Among them, 14 started presenting with apnea from median 3.5 days of age (range 0-47d). In these infants with apnea, eight received respiratory support of positive pressure ventilation (PPV). The 1-year survival rate of infants in the PPV group was higher than that of non-PPV-supported infants (5 out of 8 vs 0 out of 6 infants). Five PPV-supported infants received a diagnosis of epilepsy, which was controlled by antiepileptic drugs. Postnatal respiratory intervention provides better prognosis in infants with trisomy 18. Improved survival leads to accurate diagnosis and treatment of apneic events in association with epilepsy. WHAT THIS PAPER ADDS: Respiratory support is effective against apnea in infants with trisomy 18. Intervention with ventilation provides a higher chance of prolonged survival. Improved survival leads to the accurate diagnosis and treatment of epilepsy-associated apnea. | F54: Dev Med Child Neurol | G54: Journal Article; Observational Study; Research Support, Non-U.S. Gov't | H54: A | I54: Incluir | J54: A | M54: Mesma instituição de Inoue et al. 2021: possível sobreposição de pacientes. | N54: =HYPERLINK("https://pubmed.ncbi.nlm.nih.gov/31763690/","abrir") -> abrir | O54: =IF(B54 < 2024, FALSE() , TRUE()) -> FALSE
A55: 31954556 | B55: 2020 | C55: Iida C | D55: Impacts of surgical interventions on the long-term outcomes in individuals with trisomy 18. | E55: OBJECTIVE: We aim to clarify whether surgical interventions can contribute to improve the long-term outcomes among individuals with trisomy 18. METHODS: We retrospectively studied 69 individuals with trisomy 18 admitted to 4 tertiary neonatal centers between 2003 and 2017. A cohort was divided into two groups: subjects with surgical interventions and conservative treatments. We compared the rates of survival and achieving homecare between the groups. RESULTS: Gestational age and birth weight were 37 (27-43) weeks and 1,700 (822-2,546) g, respectively. There were 68 patients with congenital heart disease and 20 patients with digestive disease. Surgical interventions including cardiac and digestive surgery were provided in 41% of individuals. There was no difference in gestational age (p=0.30), birth weight (p=0.07), gender (p=0.30), and fetal diagnosis (p=0.87) between the groups. During the median follow up duration of 51 (2-178) months, overall survival rates in 6, 12 and 60 months were 57%, 43% and 12%, respectively. Survival to hospital discharge occurred in 23 patients, and the rates of achieving homecare in 1, 6, and 12 months are 1%, 18% and 30%, respectively. There was no significant difference in survival rate (p=0.26) but in the rate of achieving home care (p=0.02) between the groups. Cox hazard analysis revealed that prenatal diagnosis (hazard ratio 0.30, 95%CI: 0.13-0.75), cardiac surgery (hazard ratio 2.40, 95%CI:,1.03-5.55), and digestive surgery (hazard ratio 1.20, 95%CI: 1.25-3.90) were related to the rate of achieving homecare. CONCLUSION: Aggressive surgical interventions contribute not to the long-term survival but to achieve homecare among individuals with trisomy 18. EVIDENCE LEVEL: Level 3 (Prognostic study, Case-Control study). | F55: J Pediatr Surg | G55: Journal Article | H55: A | I55: Incluir | J55: A | N55: =HYPERLINK("https://pubmed.ncbi.nlm.nih.gov/31954556/","abrir") -> abrir | O55: =IF(B55 < 2024, FALSE() , TRUE()) -> FALSE
A56: 32815676 | B56: 2020 | C56: Murphy NC | D56: Prenatally Diagnosed Fetal Aneuploidy: Natural History and Subsequent Management. | E56: Aims Our aim was to determine the number of cases of aneuploidy which were prenatally diagnosed in our tertiary referral unit from 2005-2015 and to analyse the subsequent outcomes of Trisomies 13, 18 and 21(T13, T18 and T21). Methods This was a retrospective observational study. We firstly determined the total number of prenatally diagnosed aneuploidies. We then analysed their subsequent outcomes including average gestation at miscarriage or IUD, mode of delivery and neonatal outcome. Results 402 cases of T13, T18 or T21 were identified of which 40% opted for expectant management. T18 was the most likely diagnosis to result in miscarriage, IUD or intrapartum death. The highest caesarean delivery rate was in T21. Conclusion With regards to T13 and T18, live birth rates show that some parents may achieve the goal of spending time with their baby in the immediate postpartum period. This information will act as a valuable resource in our counselling. | F56: Ir Med J | G56: Journal Article | H56: B | I56: Incluir | J56: B | N56: =HYPERLINK("https://pubmed.ncbi.nlm.nih.gov/32815676/","abrir") -> abrir | O56: =IF(B56 < 2024, FALSE() , TRUE()) -> FALSE
A57: 32986711 | B57: 2020 | C57: Glinianaia SV | D57: Long-term survival of children born with congenital anomalies: A systematic review and meta-analysis of population-based studies. | E57: BACKGROUND: Following a reduction in global child mortality due to communicable diseases, the relative contribution of congenital anomalies to child mortality is increasing. Although infant survival of children born with congenital anomalies has improved for many anomaly types in recent decades, there is less evidence on survival beyond infancy. We aimed to systematically review, summarise, and quantify the existing population-based data on long-term survival of individuals born with specific major congenital anomalies and examine the factors associated with survival. METHODS AND FINDINGS: Seven electronic databases (Medline, Embase, Scopus, PsycINFO, CINAHL, ProQuest Natural, and Biological Science Collections), reference lists, and citations of the included articles for studies published 1 January 1995 to 30 April 2020 were searched. Screening for eligibility, data extraction, and quality appraisal were performed in duplicate. We included original population-based studies that reported long-term survival (beyond 1 year of life) of children born with a major congenital anomaly with the follow-up starting from birth that were published in the English language as peer-reviewed papers. Studies on congenital heart defects (CHDs) were excluded because of a recent systematic review of population-based studies of CHD survival. Meta-analysis was performed to pool survival estimates, accounting for trends over time. Of 10,888 identified articles, 55 (n = 367,801 live births) met the inclusion criteria and were summarised narratively, 41 studies (n = 54,676) investigating eight congenital anomaly types (spina bifida [n = 7,422], encephalocele [n = 1,562], oesophageal atresia [n = 6,303], biliary atresia [n = 3,877], diaphragmatic hernia [n = 6,176], gastroschisis [n = 4,845], Down syndrome by presence of CHD [n = 22,317], and trisomy 18 [n = 2,174]) were included in the meta-analysis. These studies covered birth years from 1970 to 2015. Survival for children with spina bifida, oesophageal atresia, biliary atresia, diaphragmatic hernia, gastroschisis, and Down syndrome with an associated CHD has significantly improved over time, with the pooled odds ratios (ORs) of surviving per 10-year increase in birth year being OR = 1.34 (95% confidence interval [95% CI] 1.24-1.46), OR = 1.50 (95% CI 1.38-1.62), OR = 1.62 (95% CI 1.28-2.05), OR = 1.57 (95% CI 1.37-1.81), OR = 1.24 (95% CI 1.02-1.5), and OR = 1.99 (95% CI 1.67-2.37), respectively (p < 0.001 for all, except for gastroschisis [p = 0.029]). There was no observed improvement for children with encephalocele (OR = 0.98, 95% CI 0.95-1.01, p = 0.19) and children with biliary atresia surviving with native liver (OR = 0.96, 95% CI 0.88-1.03, p = 0.26). The presence of additional structural anomalies, low birth weight, and earlier year of birth were the most commonly reported predictors of reduced survival for any congenital anomaly type. The main limitation of the meta-analysis was the small number of studies and the small size of the cohorts, which limited the predictive capabilities of the models resulting in wide confidence intervals. CONCLUSIONS: This systematic review and meta-analysis summarises estimates of long-term survival associated with major congenital anomalies. We report a significant improvement in survival of children with specific congenital anomalies over the last few decades and predict survival estimates up to 20 years of age for those born in 2020. This information is important for the planning and delivery of specialised medical, social, and education services and for counselling affected families. This trial was registered on the PROSPERO database (CRD42017074675). | F57: PLoS Med | G57: Journal Article; Meta-Analysis; Research Support, Non-U.S. Gov't; Systematic Review | H57: A | I57: Incluir | J57: A | M57: Destaque: revisão sistemática de estudos populacionais sobre sobrevida de longo prazo. | N57: =HYPERLINK("https://pubmed.ncbi.nlm.nih.gov/32986711/","abrir") -> abrir | O57: =IF(B57 < 2024, FALSE() , TRUE()) -> FALSE
A58: 30291384 | B58: 2019 | C58: Domingo L | D58: Mortality and Resource Use Following Cardiac Interventions in Children with Trisomy 13 and Trisomy 18 and Congenital Heart Disease. | E58: We sought to evaluate the mortality, risk factors for mortality, and resource utilization following cardiac interventions in trisomy 13 (T13) and 18 (T18) children. All T13 and T18 children who underwent a cardiac intervention from January 1999 to March 2015 were identified from the Pediatric Health Information System database. Data collected included demographics, type of congenital heart disease (CHD), cardiac interventions, comorbidities, length of stay (LOS), hospital charges, and deaths (within 30 days). Logistic regression analysis was used to determine factors associated with mortality. There were 49 (47% females) T13 and 140 (67% females) T18 subjects. The two cohorts were similar in distribution for race, geographic region, insurance type, and median household income. The most common CHD in both groups was a shunt lesion followed by conotruncal defects. Compared to T18, the T13 cohort had higher mortality (29% vs. 12%), tracheostomies (12% vs. 4%), gastrostomies (18% vs. 6%), and overall resource use (P < 0.05 for all). White race (OR 0.23, 95% CI 0.06-0.81) in T13 and older age (in weeks) at surgery in T18 (OR 0.75, 95% CI 0.64-0.86) were associated with lower mortality. A select group of T13 and T18 CHD patients can undergo successful cardiac interventions, albeit with a higher mortality and resource use. T13 patients have higher mortality and resource use compared to T18. In T13 and T18 patients, interventions for CHD may be an acceptable and ethical option following a careful individualized selection and counseling by a team of experts. | F58: Pediatr Cardiol | G58: Journal Article; Multicenter Study | H58: A | I58: Incluir | J58: A | N58: =HYPERLINK("https://pubmed.ncbi.nlm.nih.gov/30291384/","abrir") -> abrir | O58: =IF(B58 < 2024, FALSE() , TRUE()) -> FALSE
A59: 30556105 | B59: 2019 | C59: Ma MH | D59: Congenital Heart Surgical Admissions in Patients with Trisomy 13 and 18: Frequency, Morbidity, and Mortality. | E59: Congenital heart defects are common among patients with trisomy 13 and 18; surgical repair has been controversial and rarely studied. We aimed to assess the frequency of cardiac surgery among admissions with trisomy 13 and 18, and evaluate their associations with resource use, complications, and mortality compared to admissions without these diagnoses. We evaluated congenital heart surgery admissions of ages < 18 years in the 1997, 2000, 2003, 2006, and 2009 Kids' Inpatient Database. Bivariate and multivariate analyses examined the adjusted association of trisomy 13 and 18 on resource use, complications, and inpatient death following congenital heart surgery. Among the 73,107 congenital heart surgery admissions, trisomy 13 represented 0.03% (n = 22) and trisomy 18 represented 0.08% (n = 58). Trisomy 13 and 18 admissions were longer; trisomy 13: 27 days vs. 8 days, p = 0.003; trisomy 18: 16 days vs. 8 days, p = 0.001. Hospital charges were higher for trisomy 13 and 18 admissions; trisomy 13: $160,890 vs. $87,007, p = 0.010; trisomy 18: $160,616 vs. $86,999, p < 0.001. Trisomy 18 had a higher complication rate: 52% vs. 34%, p < 0.006. For all cardiac surgery admissions, mortality was 4.5%; trisomy 13: 14% and trisomy 18: 12%. In multivariate analysis, trisomy 18 was an independent predictor of death: OR 4.16, 95% CI 1.35-12.82, p = 0.013. Patients with trisomy 13 and 18 represent 0.11% of pediatric congenital heart surgery admissions. These patients have a 2- to 3.4-fold longer hospital stay and double hospital charges. Patients with trisomy 18 have more complications and four times greater adjusted odds for inpatient death. | F59: Pediatr Cardiol | G59: Journal Article; Multicenter Study | H59: A | I59: Incluir | J59: A | N59: =HYPERLINK("https://pubmed.ncbi.nlm.nih.gov/30556105/","abrir") -> abrir | O59: =IF(B59 < 2024, FALSE() , TRUE()) -> FALSE
A60: 30932336 | B60: 2019 | C60: Mullin J | D60: Experiences of children with trisomy 18 referred to pediatric palliative care services on two continents. | E60: Children with trisomy 18 that survive beyond the neonatal period have multiple congenital anomalies, neurodevelopmental disability, and high mortality rates. The experience of children with trisomy 18 who receive pediatric palliative care services is largely unknown. We conducted a retrospective review of children with trisomy 18 receiving pediatric palliative care services at both Boston Children's Hospital, USA and Great Ormond Street Hospital, UK from January 1, 2004 to January 1, 2015. Fifty-eight children with trisomy 18 were referred to pediatric palliative care, 38 in the United Kingdom, 20 in the United States. Median age at referral was 19 days (2-89) in the United Kingdom, and 25 days (1-463) in the United States. Median length of time being followed by pediatric palliative care was 32 days (1-1,637) in the United Kingdom and 67 days (3-2,442) in the United States. The only significant difference in the two cohorts (p = .001) was in likelihood of receiving cardiac surgical intervention-37% in the United States, 0% the United Kingdom. Children with trisomy 18 receive pediatric palliative care services, with variable age at referral and for a variable length of time. Further research is needed to understand the experience of children with trisomy 18 and their families receiving pediatric palliative care services. | F60: Am J Med Genet A | G60: Journal Article; Research Support, Non-U.S. Gov't | H60: A | I60: Incluir | J60: A | N60: =HYPERLINK("https://pubmed.ncbi.nlm.nih.gov/30932336/","abrir") -> abrir | O60: =IF(B60 < 2024, FALSE() , TRUE()) -> FALSE
A61: 30935949 | B61: 2019 | C61: Haghnazarian E | D61: The association of Trisomy 13 and 18 and hospital discharge outcomes among neonates in California: A retrospective cohort study. | E61: BACKGROUND: Despite Trisomy 13 and 18 being among the most fatal congenital anomalies, limited information exists about resource utilization and factors associated with length of stay (LOS) and total hospital charges (THC) for these anomalies. METHODS: We studied data sets of the patient discharge data set from the California Office of Statewide Health Planning and Development from 2006 to 2010, to determine differences in resource utilization for survivors and non-survivors and identify the predictors of LOS and total hospital charges. Descriptive statistics were assessed for demographic and clinical characteristics. General linear regression models were used to identify predictors of LOS and THC. RESULTS: Seventy-six Trisomy 13 and 115 Trisomy 18 patients were identified, for whom inpatient mortality was 27.6% and 20.9%, respectively. In patients with Trisomy 13, after adjusting for gender, ethnicity, advanced directive (DNR), insurance and co-morbidities on multivariate analysis, the provision of more than 96 h of mechanical ventilation was associated with significantly increased LOS (standard error, SE) by 18.0 ± 5.3 days and THC (SE) by $399,000 ± $85,000. In terms of insurance type, patients with private coverage had 10.8 ± 4.9 days more than patients with Medicaid. In patients with Trisomy 18, on multivariate analysis, after adjusting for gender, ethnicity, DNR, insurance and co-morbidities, more than 96 h of mechanical ventilation was associated with increased LOS (SE) by 36.8 ± 6.8 days and THC (SE) by $365,000 ± $59,000. CONCLUSION: Understanding predictors that are associated with longer LOS and higher THC may be associated in hospital resource allocation for this vulnerable population of infants. | F61: Pediatr Neonatol | G61: Journal Article; Research Support, N.I.H., Extramural | H61: A | I61: Incluir | J61: A | N61: =HYPERLINK("https://pubmed.ncbi.nlm.nih.gov/30935949/","abrir") -> abrir | O61: =IF(B61 < 2024, FALSE() , TRUE()) -> FALSE
A62: 30942556 | B62: 2019 | C62: Kato E | D62: Factors related to survival discharge in trisomy 18: A retrospective multicenter study. | E62: Infants with trisomy 18 (T18) previously had a poor prognosis; however, the intensive care of these patients has markedly diversified the prognosis. We investigated the current situation of patients with T18, clarified factors for survival discharge, and surveyed actual home healthcare. A total of 117 patients with T18 admitted to nine institutions between 2000 and 2015 were retrospectively investigated. After excluding four patients whose outcomes were unclear, we divided 113 patients into two groups-the survival discharge group (n = 52) and the death discharge group (n = 61)-and compared maternal factors, perinatal factors, neonatal factors, and therapeutic factors between the groups. In addition, home healthcare, readmission, utilization of respite care and home nursing, and cause of death among the survival group were surveyed. Fifty-two (44%) patients with T18 survived at discharge and their 1-year survival rate was 29%. The survival group had a longer gestation period, larger physique, and longer survival time, compared to the death group. Independent factors associated with survival discharge were the absence of an extremely low birthweight infant (ELBWI), the absence of esophageal atresia and patent ductus arteriosus, and cardiovascular surgery. All surviving patients required some home healthcare. The most frequent cause of death was a respiratory disorder. We recommend discussing the treatment strategy with families in the presence of neonatologists or pediatric surgeons, who can explain differences in prognosis, based on the gestation period, birthweight, severity of cardiovascular disease, and cardiovascular surgery. | F62: Am J Med Genet A | G62: Journal Article; Multicenter Study | H62: A | I62: Incluir | J62: A | N62: =HYPERLINK("https://pubmed.ncbi.nlm.nih.gov/30942556/","abrir") -> abrir | O62: =IF(B62 < 2024, FALSE() , TRUE()) -> FALSE
A63: 31170277 | B63: 2019 | C63: Duque JAP | D63: The natural history of pregnancies with prenatal diagnosis of Trisomy 18 or Trisomy 13: Retrospective cases of a 23-year experience in a Brazilian public hospital. | E63: Trisomy 18 (T18) and trisomy 13 (T13) are polymalformative syndromes associated with a high rate of spontaneous abortions, intrauterine death, and short postnatal life. This study describes the overall outcome in a country where the therapeutic interruption of pregnancy is not available. The medical records of women with prenatal diagnosis of full trisomy of T13 or T18 between October 1994 and October 2017 were analyzed in order to describe their natural outcomes. Thirteen cases of T13 and 29 cases of T18 were included. The miscarriage rate was 9% for T18 and no cases for T13. Intrauterine fetal death occurred in 46% and 52% of cases for T13 and T18, respectively. The rate of live births for T13 was 54%, and the median survival was one day (95% CI -33.55 - 90.40) and 71% died in the first 24 hours of life. The rate of live births for T18 was 37% and the median survival was two days (95% CI -1.89 - 13.17); 90% of the affected babies died within first week of life. For the affected babies reaching the first year of life and for those who lived longer, multiple invasive and expensive procedures were required, without success in prolonging life beyond 180 days. This large series provides information for professionals and women regarding the natural histories of T13 and T18. Results of this study are consistent with those referenced in the literature, emphasizing the need of structured protocols and guidelines aiming early T13 and T18 diagnosis, prenatal care, gestation/parents follow-up, and counseling processes. For those couples with earlier diagnosis, a better follow-up and counseling during the prenatal care lead to the option for a support or palliative management of the newborn. Finally, when the counseling process is appropriate, it becomes easier to take decisions respecting the parent's autonomy and to look for better outcomes for both, the mother and the fetus. | F63: Genet Mol Biol | G63: Journal Article | H63: A+B | I63: Incluir | J63: A+B | M63: Dados brasileiros (Porto Alegre). | N63: =HYPERLINK("https://pubmed.ncbi.nlm.nih.gov/31170277/","abrir") -> abrir | O63: =IF(B63 < 2024, FALSE() , TRUE()) -> FALSE
A64: 31237190 | B64: 2019 | C64: Cooper DS | D64: Cardiac Surgery in Patients With Trisomy 13 and 18: An Analysis of The Society of Thoracic Surgeons Congenital Heart Surgery Database. | E64: Background Congenital heart disease is common in patients with Trisomy 13 (T13) and Trisomy 18 (T18), but offering cardiac surgery to these patients has been controversial. We describe the landscape of surgical management across the United States, perioperative risk factors, and surgical outcomes in patients with T13 and T18. Methods and Results Patients in the Society of Thoracic Surgeons Congenital Heart Surgery Database with T13 and T18 who underwent cardiac surgery (2010-2017) were included. There were 343 operations (T13: n=73 and T18: n=270) performed on 304 patients. Among 125 hospitals, 87 (70%) performed at least 1 operation and 26 centers (30%) performed ≥5 T13/T18 operations. Operations spanned the full spectrum of complexity with 29% (98/343) being in the highest categories of estimated risk. The operative mortality rate was 15%, with a 56% complication rate. Preoperative mechanical ventilation was associated with an odds ratio of mortality >8 for both patients with T13 and T18 (both P<0.012) while presence of a gastrostomy tube (odds ratio, 0.3; P=0.03) or prior cardiac surgery (odds ratio, 0.2; P=0.02) was associated with better survival in patients with T18 but not patients with T13. Conclusions Data from this nationally representative sample indicate that most centers offer surgical intervention for both patients with T13 and T18, even in highly complex patients. However, the overall mortality rate was high in this select patient cohort. The association of preoperative mechanical ventilation with mortality suggests that this subset of patients with T13 and T18 should perhaps not be considered surgical candidates. This information is valuable to clinicians and families for counseling and deciding what interventions to offer. | F64: J Am Heart Assoc | G64: Journal Article | H64: A | I64: Incluir | J64: A | N64: =HYPERLINK("https://pubmed.ncbi.nlm.nih.gov/31237190/","abrir") -> abrir | O64: =IF(B64 < 2024, FALSE() , TRUE()) -> FALSE
A65: 31566869 | B65: 2019 | C65: Goel N | D65: Trisomy 13 and 18-Prevalence and mortality-A multi-registry population based analysis. | E65: The aim of the study is to determine the prevalence, outcomes, and survival (among live births [LB]), in pregnancies diagnosed with trisomy 13 (T13) and 18 (T18), by congenital anomaly register and region. Twenty-four population- and hospital-based birth defects surveillance registers from 18 countries, contributed data on T13 and T18 between 1974 and 2014 using a common data-reporting protocol. The mean total birth prevalence (i.e., LB, stillbirths, and elective termination of pregnancy for fetal anomalies [ETOPFA]) in the registers with ETOPFA (n = 15) for T13 was 1.68 (95% CI 1.3-2.06), and for T18 was 4.08 (95% CI 3.01-5.15), per 10,000 births. The prevalence varied among the various registers. The mean prevalence among LB in all registers for T13 was 0.55 (95%CI 0.38-0.72), and for T18 was 1.07 (95% CI 0.77-1.38), per 10,000 births. The median mortality in the first week of life was 48% for T13 and 42% for T18, across all registers, half of which occurred on the first day of life. Across 16 registers with complete 1-year follow-up, mortality in first year of life was 87% for T13 and 88% for T18. This study provides an international perspective on prevalence and mortality of T13 and T18. Overall outcomes and survival among LB were poor with about half of live born infants not surviving first week of life; nevertheless about 10% survived the first year of life. Prevalence and outcomes varied by country and termination policies. The study highlights the variation in screening, data collection, and reporting practices for these conditions. | F65: Am J Med Genet A | G65: Journal Article; Research Support, Non-U.S. Gov't | H65: A+B | I65: Incluir | J65: A+B | N65: =HYPERLINK("https://pubmed.ncbi.nlm.nih.gov/31566869/","abrir") -> abrir | O65: =IF(B65 < 2024, FALSE() , TRUE()) -> FALSE
A66: 28948390 | B66: 2018 | C66: Peterson R | D66: Factors Influencing Outcomes After Cardiac Intervention in Infants with Trisomy 13 and 18. | E66: Cardiac intervention remains controversial in patients with trisomy 13 and 18 and little is known about factors that may affect outcomes. The goal of this study was to evaluate preoperative factors and surgical approach with respect to outcomes in these patients. Patients with congenital heart disease and trisomy 13 or 18 presenting to our institution from 2004 through 2015 were retrospectively reviewed. Patients were grouped into complete intervention, palliated intervention, and non-intervention. Pre-intervention variables, timing and type of intervention, post-intervention outcomes, and survival were recorded and comparisons were made between the groups. Of 34 patients, 18 cardiac interventions were performed. Complete repair was performed in 11(61%) and palliation in 7(39%). Median age for complete repair was 9.2 vs. 1.7 months in palliated patients (p < 0.001) and palliated patients were smaller (median 2.5 vs. 5.2 kg, p < 0.001). All patients who underwent complete repair survived to discharge compared to only 57% of patients that were palliated (p = 0.04). Palliated patients had longer intubation and time to discharge (p < 0.05). Survival at last follow-up was greater in the complete repair group compared with palliated patients and non-intervention patients (72, 14, and 18%, p = 0.009) with a longer median length of survival in the complete repair group (p = 0.002). In our group of trisomy 13 and 18 patients, those able to undergo complete repair had improved outcomes. Patients undergoing complete repair were older and bigger; this suggests that delaying intervention and optimizing the likelihood of complete repair may be beneficial. | F66: Pediatr Cardiol | G66: Journal Article; Observational Study | H66: A | I66: Incluir | J66: A | N66: =HYPERLINK("https://pubmed.ncbi.nlm.nih.gov/28948390/","abrir") -> abrir | O66: =IF(B66 < 2024, FALSE() , TRUE()) -> FALSE
A67: 29112995 | B67: 2018 | C67: Akgün Doğan Ö | D67: Prenatal and Postnatal Follow-up in Trisomies 13 and 18: A 20-Year Experience in a Tertiary Center. | E67: OBJECTIVE: Trisomies 13 and 18 are among the most common autosomal aneuploidies associated with high mortality rates. Conventional management strategies offer to limit interventional support; however, some of the recent studies suggest that intervention does make a difference in terms of survival. STUDY DESIGN: A retrospective cohort study was performed between January 1996 and January 2016, covering all cases with such trisomies. A total of 69 cases were reviewed for clinical aspects, outcome, and management strategies. RESULTS: In almost all pregnancies with follow-up, at least one indication present for invasive testing (54/55). Invasive testing was not performed in 18.5% of such cases. All parents opted for termination in cases with prenatal diagnosis. None of the liveborns had prenatal diagnoses, thus, neonatal resuscitation and intensive care unit admission were not withheld in such infants. Major intervention was done in only one patient with full trisomy 13. Median survival for infants with full trisomies 13 and 18 was 36 and 60 days, respectively. Almost half the patients died within 1 month. CONCLUSION: To which extent the major interventions should be withheld is an issue of debate in managing such infants; however, current approaches are subject to change, given the technological advances. | F67: Am J Perinatol | G67: Journal Article | H67: A | I67: Incluir | J67: A+B | N67: =HYPERLINK("https://pubmed.ncbi.nlm.nih.gov/29112995/","abrir") -> abrir | O67: =IF(B67 < 2024, FALSE() , TRUE()) -> FALSE
A68: 29740195 | B68: 2018 | C68: Winn P | D68: Prenatal counseling and parental decision-making following a fetal diagnosis of trisomy 13 or 18. | E68: OBJECTIVES: To evaluate parental decisions following a prenatal diagnosis of trisomy 13 (T13) or trisomy 18 (T18), prenatal counseling received, and pregnancy outcomes. STUDY DESIGN: Single-center, retrospective cohort study of families with a prenatal diagnosis of T13 or T18 from 2000 to 2016. RESULTS: Out of 152 pregnancies, 55% were terminated. Twenty percent chose induction with palliative care, 20% chose expectant management, 2% chose full interventions, and 3% were lost to follow-up. Counseling was based on initial parental goals, but most women were given options besides termination. Women who chose expectant management had a live birth in 50% of the cases. Women who chose neonatal interventions had a live birth in 100% of the cases, but there were no long-term survivors. CONCLUSIONS: The majority of women who continue their pregnancy after a fetal diagnosis of T13 or T18 desire expectant management with palliative care. A live birth can be expected at least half of the time. | F68: J Perinatol | G68: Comparative Study; Journal Article | H68: A+B | I68: Incluir | J68: A+B | M68: Desfechos por decisão parental após diagnóstico pré-natal. | N68: =HYPERLINK("https://pubmed.ncbi.nlm.nih.gov/29740195/","abrir") -> abrir | O68: =IF(B68 < 2024, FALSE() , TRUE()) -> FALSE
A69: 30237475 | B69: 2018 | C69: Nguyen JE | D69: Survival and healthcare utilization of infants diagnosed with lethal congenital malformations. | E69: OBJECTIVE: We assessed survival, hospital length of stay (LOS), and costs of medical care for infants with lethal congenital malformations, and also examined the relationship between medical and surgical therapies and survival. STUDY DESIGN: Retrospective cohort study including infants born 1998-2009 with lethal congenital malformations, identified using a longitudinally linked maternal/infant database. RESULTS: The cohort included 786 infants: trisomy 18 (T18, n = 350), trisomy 13 (T13, n = 206), anencephaly (n = 125), bilateral renal agenesis (n = 53), thanatophoric dysplasia/achondrogenesis/lethal osteogenesis imperfecta (n = 38), and infants > 1 of the birth defects (n = 14). Compared to infants without birth defects, infants with T18, T13, bilateral renal agenesis, and skeletal dysplasias had longer survival rates, higher inpatient medical costs, and longer LOS. CONCLUSION: Care practices and survival have changed over time for infants with T18, T13, bilateral renal agenesis, and skeletal dysplasias. This information will be useful for clinicians in counseling families and in shaping goals of care prenatally and postnatally. | F69: J Perinatol | G69: Journal Article | H69: A | I69: Incluir | J69: A | M69: Destaque: compara a sobrevida da T18 com a da anencefalia na mesma coorte (distinção com a ADPF 54). | N69: =HYPERLINK("https://pubmed.ncbi.nlm.nih.gov/30237475/","abrir") -> abrir | O69: =IF(B69 < 2024, FALSE() , TRUE()) -> FALSE
A70: 27490773 | B70: 2017 | C70: Dereddy NR | D70: Neonatal Hospital Course and Outcomes of Live-born Infants with Trisomy 18 at Two Tertiary Care Centers in the United States. | E70: Objectives Trisomy 18 is presumed to be a lethal chromosomal abnormality; medical management of infants with this aneuploidy is controversial. Our objective was to describe our approach and experience with trisomy 18 infants. Study Design We reviewed the initial hospital course, management, and factors predicting discharge from the hospital from two large tertiary care neonatal intensive care units in the southern United States over 26 years. Results Of the 29 infants with trisomy 18, 21 (72%) died in the hospital and 8 (28%) were discharged home. 19 (66%) infants received mechanical ventilation and 10 (34%) received inotropic medications. Eight infants had critical congenital heart defects; only one survived to discharge. Three infants underwent major surgeries; one cardiac surgery, one tracheoesophageal fistula repair, and one myelomeningocele repair. Median length of hospital stay was 14 days (range, 0-78) for all the infants and 31 days (range, 18-66) for those that were discharged home. Factors associated with discharge from the hospital were female sex, higher gestational age, and absence of critical congenital heart defects. Median survival time was 13 days and was significantly longer for females compared with males. Our 1-month and 1-year survival rates were 31% and 3.9% respectively. Conclusion A significant proportion of infants with trisomy 18 were discharged home. These data are helpful in counseling parents of infants with trisomy 18. | F70: Am J Perinatol | G70: Journal Article; Multicenter Study | H70: A | I70: Incluir | J70: A | N70: =HYPERLINK("https://pubmed.ncbi.nlm.nih.gov/27490773/","abrir") -> abrir | O70: =IF(B70 < 2024, FALSE() , TRUE()) -> FALSE
A71: 27591300 | B71: 2017 | C71: McDonnell R | D71: Epidemiology of chromosomal trisomies in the East of Ireland. | E71: BACKGROUND: Chromosomal trisomies are associated with advancing maternal age. In Ireland, information on the total prevalence and outcome of trisomy affected pregnancies is unavailable. This study aimed to ascertain more precise data on Trisomies 21, 18 and 13 in a large Irish region during the period 2011-2013. METHODS: Multiple information sources were used in case finding, including a regional congenital anomaly register, all maternity and paediatric hospitals in the region and the regional Department of Clinical Genetics. RESULTS: There were 394 trisomy cases from 80 894 total births, of which 289 were Trisomy 21, 75 were Trisomy 18 and 30 were Trisomy 13. The total prevalence rate was 48.9/10 000 births, 35.7, 9.3 and 3.7 for Trisomies 21, 18 and 13, respectively. Over 90% of Trisomies 18/13 and 47% of Trisomy 21 were diagnosed prenatally; 61% of Trisomy 21 cases and nearly 30% of Trisomies 18/13 were live births; 38% all trisomy affected pregnancies ended in a termination. CONCLUSIONS: This study provides precise data on the total prevalence and outcome of trisomy affected pregnancies in the East of Ireland. Total prevalence rates were higher than previously reported. Prenatal diagnosis had a significant impact on outcome. These data provide a better basis for planning of services for live-born children affected by trisomy. | F71: J Public Health (Oxf) | G71: Journal Article | H71: B | I71: Incluir | J71: B | M71: Verificar no texto completo se há dado específico e separável da T18 Irlanda (aborto então não permitido): desfechos de gestações com trissomias. | N71: =HYPERLINK("https://pubmed.ncbi.nlm.nih.gov/27591300/","abrir") -> abrir | O71: =IF(B71 < 2024, FALSE() , TRUE()) -> FALSE
A72: 28056858 | B72: 2017 | C72: Bouman K | D72: The impact of national prenatal screening on the time of diagnosis and outcome of pregnancies affected with common trisomies, a cohort study in the Northern Netherlands. | E72: BACKGROUND: To evaluate the impact of the introduction of prenatal screening on time of detection and pregnancy outcome for trisomy 21 (T21), trisomy 18 (T18) and trisomy 13 (T13). METHODS: We performed a retrospective, population-based cohort study in the Northern Netherlands including 503 trisomy cases born between 2005 and 2012. Screening tests and invasive procedures, timing of diagnosis and pregnancy outcome were compared between the period before (2005-2006) and after introduction (2007-2012) using X 2 tests. RESULTS: There was an increase in proportion of women who had a prenatal screening and/or invasive test, from 62% in 2005-2006 to 84% in 2010-2012 (p < 0.01), while the proportion of prenatally diagnosed cases did not change (60% overall). In women < =35 years 47% of the cases were diagnosed prenatally vs 73% in women >35 years (p < 0.01). More T13/T18 cases were diagnosed <24 weeks after introduction (62% vs 84%; p < 0.01). In T13/T18 intra-uterine death decreased (26% vs 15%), while terminations increased: 55% vs 72%. CONCLUSION: The introduction of prenatal screening had limited impact on the time of detection and outcome of the most common trisomies. The introduction of the 20-week anomaly scan has resulted in more trisomy cases diagnosed <24 weeks and a shift from fetal death to terminations. | F72: BMC Pregnancy Childbirth | G72: Evaluation Study; Journal Article | H72: B | I72: Incluir | J72: B | M72: Verificar no texto completo se há dado específico e separável da T18 | N72: =HYPERLINK("https://pubmed.ncbi.nlm.nih.gov/28056858/","abrir") -> abrir | O72: =IF(B72 < 2024, FALSE() , TRUE()) -> FALSE
A73: 28079873 | B73: 2017 | C73: Acharya K | D73: Major anomalies and birth-weight influence NICU interventions and mortality in infants with trisomy 13 or 18. | E73: OBJECTIVE: To describe neonatal intensive care unit (NICU) medical interventions and NICU mortality by birth weight and major anomaly types for infants with trisomy 13 (T13) or 18 (T18). STUDY DESIGN: Retrospective cohort analysis of infants with T13 or T18 from 2005 to 2012 in the Pediatrix Medical Group. We classified infants into three groups by associated anomaly type: neonatal surgical, non-neonatal surgical and minor. Outcomes were NICU medical interventions and mortality. RESULTS: 841 infants were included from 186 NICUs. NICU mortality varied widely by anomaly type and birth weight, from 70% of infants <1500 g with neonatal surgical anomalies to 31% of infants ⩾2500 g with minor anomalies. Infants ⩾1500 g without a neonatal surgical anomaly comprised 66% of infants admitted to the NICU; they had the lowest rates of NICU medical interventions and NICU mortality. CONCLUSIONS: Risk stratification by anomaly type and birth weight may help provide more accurate family counseling for infants with T13 and T18. | F73: J Perinatol | G73: Journal Article; Multicenter Study | H73: A | I73: Incluir | J73: A | N73: =HYPERLINK("https://pubmed.ncbi.nlm.nih.gov/28079873/","abrir") -> abrir | O73: =IF(B73 < 2024, FALSE() , TRUE()) -> FALSE
A74: 28328132 | B74: 2017 | C74: Cavadino A | D74: Revised estimates of the risk of fetal loss following a prenatal diagnosis of trisomy 13 or trisomy 18. | E74: Edwards syndrome (trisomy 18) and Patau syndrome (trisomy 13) both have high natural fetal loss rates. The aim of this study was to provide estimates of these fetal loss rates by single gestational week of age using data from the National Down Syndrome Cytogenetic Register. Data from all pregnancies with Edwards or Patau syndrome that were prenatally detected in England and Wales from 2004 to 2014 was analyzed using Kaplan-Meier survival estimates. Pregnancies were entered into the analysis at the time of gestation at diagnosis, and were considered "under observation" until the gestation at outcome. There were 4088 prenatal diagnoses of trisomy 18 and 1471 of trisomy 13 in the analysis. For trisomy 18, 30% (95%CI: 25-34%) of viable fetuses at 12 weeks will result in a live birth and at 39 weeks gestation 67% (60-73%) will result in a live birth. For trisomy 13 the survival is 50% (41-58%) at 12 weeks and 84% (73-90%) at 39 weeks. There was no significant difference in survival between males and females when diagnosed at 12 weeks for trisomy 18 (P-value = 0.27) or trisomy 13 (P-value = 0.47). This paper provides the most precise gestational age-specific estimates currently available for the risk of fetal loss in trisomy 13 and trisomy 18 pregnancies in a general population. | F74: Am J Med Genet A | G74: Journal Article | H74: A+B | I74: Incluir | J74: B | N74: =HYPERLINK("https://pubmed.ncbi.nlm.nih.gov/28328132/","abrir") -> abrir | O74: =IF(B74 < 2024, FALSE() , TRUE()) -> FALSE
A75: 28456396 | B75: 2017 | C75: Peterson JK | D75: Long-Term Outcomes of Children With Trisomy 13 and 18 After Congenital Heart Disease Interventions. | E75: BACKGROUND: The purpose of this study is to report short- and long-term outcomes after congenital heart defect (CHD) interventions in patients with trisomy 13 or 18. METHODS: A retrospective review of the Pediatric Cardiac Care Consortium (PCCC) identified children with trisomy 13 or 18 with interventions for CHD between 1982 and 2008. Long-term survival and cause of death were obtained through linkage with the National Death Index. RESULTS: A total of 50 patients with trisomy 13 and 121 patients with trisomy 18 were enrolled in PCCC between 1982 and 2008; among them 29 patients with trisomy 13 and 69 patients with trisomy 18 underwent intervention for CHD. In-hospital mortality rates for patients with trisomy 13 or trisomy 18 were 27.6% and 13%, respectively. Causes of in-hospital death were primarily cardiac (64.7%) or multiple organ system failure (17.6%). National Death Index linkage confirmed 23 deaths after discharge. Median survival (conditioned to hospital discharge) was 14.8 years (95% confidence interval [CI]: 12.3 to 25.6 years) for patients with trisomy 13 and 16.2 years (95% CI: 12 to 20.4 years) for patients with trisomy 18. Causes of late death included cardiac (43.5%), respiratory (26.1%), and pulmonary hypertension (13%). CONCLUSIONS: In-hospital mortality rate for all surgical risk categories was higher in patients with trisomy 13 or 18 than that reported for the general population. However, patients with trisomy 13 or 18, who were selected as acceptable candidates for cardiac intervention and who survived CHD intervention, demonstrated longer survival than previously reported. These findings can be used to counsel families and make program-level decisions on offering intervention to carefully selected patients. | F75: Ann Thorac Surg | G75: Journal Article | H75: A | I75: Incluir | J75: A | N75: =HYPERLINK("https://pubmed.ncbi.nlm.nih.gov/28456396/","abrir") -> abrir | O75: =IF(B75 < 2024, FALSE() , TRUE()) -> FALSE
A76: 29046387 | B76: 2017 | C76: Kosiv KA | D76: Congenital Heart Surgery on In-Hospital Mortality in Trisomy 13 and 18. | E76: BACKGROUND AND OBJECTIVES: Congenital heart disease (CHD) is common in trisomy 13 (T13) and trisomy 18 (T18), but surgical repair has not been offered in most centers. Data on outcomes of congenital heart surgery (CHS) for T13 and T18 are lacking. We sought to determine the impact of CHS on in-hospital mortality in T13 and T18. METHODS: Data from the 2004 to 2015 Pediatric Health Information System database were used to identify inpatients with T13 or T18 and CHD. Data were restricted to newborns with T13 or T18 admitted at ≤14 days of age. Hospital readmissions were examined to analyze longer-term in-hospital mortality. In-hospital mortality and length of stay were compared between infants with and without CHD and with and without CHS. RESULTS: The study cohort included 1020 infants with T18 and 648 infants with T13. CHD was present in 91% of infants with T18 and 86% of infants with T13. CHS was performed in 7% of each group. In-hospital mortality was decreased in those who underwent CHS (64% lower in T18 [P <.001]; 45% lower in T13 [P = .003]) and remained decreased throughout the 24 months of follow-up. In-hospital mortality was decreased in infants with higher weight, female sex, and older age at admission. CONCLUSIONS: CHS is associated with decreased in-hospital mortality in T18 and T13. These results suggest CHS may be beneficial in select cases. | F76: Pediatrics | G76: Journal Article; Multicenter Study | H76: A | I76: Incluir | J76: A | N76: =HYPERLINK("https://pubmed.ncbi.nlm.nih.gov/29046387/","abrir") -> abrir | O76: =IF(B76 < 2024, FALSE() , TRUE()) -> FALSE
A77: 26104883 | B77: 2016 | C77: Nagase H | D77: Fetal outcome of trisomy 18 diagnosed after 22 weeks of gestation: Experience of 123 cases at a single perinatal center. | E77: To investigate the pregnancy outcome of the fetuses with trisomy 18, we studied 123 cases of trisomy 18 who were born at our hospital from 1993 to 2009. Among them, 95.9% were diagnosed with trisomy 18 prenatally. Prenatal ultrasound findings showed fetal growth restriction in 77.2%, polyhydramnios in 63.4% and congenital heart defects in 95.1%. For 18 cases, cesarean section (C-section) was chosen, and for 75 cases, transvaginal delivery was chosen. Premature delivery occurred in 35.5%. Stillbirths occurred in 50 cases (40.7%). Fetal demise before onset of labor occurred in 30 cases and fetal demise during labor occurred in 20 cases which was 26.7% of vaginal deliveries. Among the 73 live-born infants, the survival rate for 24 h, 1 week, 1 month and 1 year were 63%, 43%, 33% and 3%. The median survival time was 3.5 days. There was no significant difference between the survival time of C-section and that of vaginal delivery. However, for the births involving breech presentation, the survival time of C-section was significantly longer than that of vaginal delivery. When the fetus is diagnosed with trisomy 18, the parents have to make many choices. These findings constitute critical information in prenatal counseling to the couples whose fetuses have been found to have trisomy 18, especially when they choose palliative approaches in the perinatal management. | F77: Congenit Anom (Kyoto) | G77: Journal Article | H77: A+B | I77: Incluir | J77: A+B | N77: =HYPERLINK("https://pubmed.ncbi.nlm.nih.gov/26104883/","abrir") -> abrir | O77: =IF(B77 < 2024, FALSE() , TRUE()) -> FALSE
A78: 26453443 | B78: 2016 | C78: Bruns DA | D78: An analysis of cardiac defects and surgical interventions in 84 cases with full trisomy 18. | E78: Trisomy 18 (Edwards syndrome) is the second most common autosomal trisomy after trisomy 21. Medical issues commonly include cardiac defects, such as ventricular septal defect (VSD) and atrial septal defect (ASD). If untreated, these conditions can contribute to the associated infant mortality. The objective of the study was review parent-reported information on 84 cases with full trisomy 18 focusing on prenatal and postnatal assessment and confirmation of cardiac defects and on subsequent treatment with cardiac surgery and post-surgery outcomes. At birth, 65 parent responses indicated the presence of VSD (77.4%), 38 ASD (45.2%), and 50 patent ductus arteriosus (PDA) (59.5%). The presence of multiple cardiac defects was also analyzed including 25 cases with VSD, ASD, and PDA at birth. The total reduced to 18 at survey completion. Twenty-four cases had one or more cardiac defects repaired for a total of 34 corrective surgeries. Age at surgery varied from 2 weeks to 41 months of age with most performed under 1 year of age. Twenty-one cases were still living at the time of survey completion (87.5%). From these date we provide recommendations and implications. | F78: Am J Med Genet A | G78: Journal Article | H78: A | I78: Incluir | J78: A | N78: =HYPERLINK("https://pubmed.ncbi.nlm.nih.gov/26453443/","abrir") -> abrir | O78: =IF(B78 < 2024, FALSE() , TRUE()) -> FALSE
A79: 26473304 | B79: 2016 | C79: Russo FM | D79: Parental counseling in trisomy 18: Novel insights in prenatal features and postnatal survival. | E79: Data on the outcome of trisomy T18 (T18) when diagnosed during pregnancy are lacking. We performed a retrospective study of pregnancies complicated by T18 diagnosed at our center and a literature search for publications on the topic, with pooled estimates of survival rates at different gestational and post-natal ages. In our series, all the 60 patients included in the analysis had prenatally detected ultrasound anomalies, which were evidenced in the first trimester or at the second trimester scan in 73% of cases. In the continued pregnancies, ultrasound findings did not correlate with prenatal or post-natal outcome. A meta-analysis of available literature and our data showed that 48% [37-60%] of fetuses were live born, and among these 39% [11-72%] survived beyond 48 hr and 11% [3-21%] beyond 1 month. Our results confirm that prenatal ultrasound has high sensitivity in detection of T18 but is not predictive of the outcome of the continued pregnancies. The data on survival support that T18, even when antenatally diagnosed, cannot be considered as a uniformly lethal syndrome. | F79: Am J Med Genet A | G79: Journal Article | H79: A+B | I79: Incluir | J79: A+B | M79: Destaque: estimativas agrupadas após diagnóstico pré-natal (48% nascidos vivos; 11% além de 1 mês). Dado desfavorável que precisa ser enfrentado. | N79: =HYPERLINK("https://pubmed.ncbi.nlm.nih.gov/26473304/","abrir") -> abrir | O79: =IF(B79 < 2024, FALSE() , TRUE()) -> FALSE
A80: 26663415 | B80: 2016 | C80: Meyer RE | D80: Survival of children with trisomy 13 and trisomy 18: A multi-state population-based study. | E80: Trisomy 13 (T13) and trisomy 18 (T18) are among the most prevalent autosomal trisomies. Both are associated with a very high risk of mortality. Numerous instances, however, of long-term survival of children with T13 or T18 have prompted some clinicians to pursue aggressive treatment instead of the traditional approach of palliative care. The purpose of this study is to assess current mortality data for these conditions. This multi-state, population-based study examined data obtained from birth defect surveillance programs in nine states on live-born infants delivered during 1999-2007 with T13 or T18. Information on children's vital status and selected maternal and infant risk factors were obtained using matched birth and death certificates and other data sources. The Kaplan-Meier method and Cox proportional hazards models were used to estimate age-specific survival probabilities and predictors of survival up to age five. There were 693 children with T13 and 1,113 children with T18 identified from the participating states. Among children with T13, 5-year survival was 9.7%; among children with T18, it was 12.3%. For both trisomies, gestational age was the strongest predictor of mortality. Females and children of non-Hispanic black mothers had the lowest mortality. Omphalocele and congenital heart defects were associated with an increased risk of death for children with T18 but not T13. This study found survival among children with T13 and T18 to be somewhat higher than those previously reported in the literature, consistent with recent studies reporting improved survival following more aggressive medical intervention for these children. © 2015 Wiley Periodicals, Inc. | F80: Am J Med Genet A | G80: Journal Article; Multicenter Study | H80: A | I80: Incluir | J80: A | N80: =HYPERLINK("https://pubmed.ncbi.nlm.nih.gov/26663415/","abrir") -> abrir | O80: =IF(B80 < 2024, FALSE() , TRUE()) -> FALSE
A81: 26728763 | B81: 2016 | C81: Subramaniam A | D81: Trisomy 18: A single-center evaluation of management trends and experience with aggressive obstetric or neonatal intervention. | E81: We conducted a retrospective cohort study including all prenatal and postnatal diagnoses of trisomy 18 (T18) from 2004 to 2014 at a single tertiary referral center in the southern United States to evaluate the natural history and perinatal outcomes associated with T18 over the past decade. We analyzed pregnancy outcome, mode of delivery, and for live-births, the number and types of neonatal interventions, and characterized interventions as aggressive or non-aggressive. Survival analyses were conducted based on mode of delivery and aggressive compared to non-aggressive interventions. A total of 167 cases of T18 were identified, 150 with available records. There were 141 (94.0%) with full T18; the remainder had mosaicism (1.3%), a translocation (0.7%), or an isochromosome 18 (4.0%). Most diagnoses were prenatal (73.3%, n = 110). Of the 150 patients, there were 54 live births: 21 (38.9%) delivered vaginally, 32 (59.3%) delivered by cesarean, and mode of delivery could not be ascertained for one. Median duration of survival was 12 days (interquartile range 3-90 days). Over time, there were no changes toward increased intervention (obstetric or neonatal). For the 49 neonates who received some intervention, there was no significant difference in survival time between neonates receiving aggressive (n = 36, median survival 24 days, interquartile range 6-247) and non-aggressive (n = 13, median survival 30 days, interquartile range 8-148) intervention (P = 0.90). There was similarly no difference in neonatal survival based on mode of delivery (P = 0.79). Survival of infants with T18 is not improved with aggressive obstetric or neonatal care. | F81: Am J Med Genet A | G81: Journal Article | H81: A+B | I81: Incluir | J81: A+B | N81: =HYPERLINK("https://pubmed.ncbi.nlm.nih.gov/26728763/","abrir") -> abrir | O81: =IF(B81 < 2024, FALSE() , TRUE()) -> FALSE
A82: 26820816 | B82: 2016 | C82: Imataka G | D82: Clinical features and survival in individuals with trisomy 18: A retrospective one-center study of 44 patients who received intensive care treatments. | E82: Trisomy 18 syndrome is a common autosomal aneuploidy chromosomal abnormality caused by the presence of extra chromosome 18 that leads to malformations of various parts of the body. In this study, we retrospectively investigated the effect of the medical progression and prognosis of 44 cases of trisomy 18, admitted to our neonatal intensive care unit between 1992 and 2013. The patients were divided into group A (n=20, 1992‑2002) and group B (n=24, 2003‑2012). Following delivery, karyotype, gender, gestational weeks, birth place, cesarean section, Apgar score and birth weight were analyzed using the Fisher's exact test, unpaired t‑test and Mann‑Whitney U test. Based on the statistical results, a comparison was made of the two groups and no significant differences were observed. Clinical data of major complications, mechanical ventilation, discharge from hospital and survival days were reviewed for the cases of trisomy 18. Of the 44 patients, 42 had cardiac anomaly, 16 had esophageal atresia, and 3 patients had brain anomaly. Ventilation treatment was performed in 29 cases (65.9%) and an increased percentage was identified in group B patients. The percentage survival was estimated using Kaplan‑Meier curves and the two groups were analyzed using the generalized Wilcoxon test. Improvement in life prognosis was observed in group B as compared to group A. The log‑rank test was used to assess survey periods of 180 days, 1 year, and the entire observation period. Although significant differences were observed for the prognosis of trisomy 18 at 180 days after birth, after 1 year and the entire survey period after birth, the significant differences were not confirmed. In conclusion, results of the present study provide information concerning genetic counseling for parents/guardians and life prognosis, prior to applying intensive management to newborns with trisomy 18. | F82: Mol Med Rep | G82: Journal Article | H82: A | I82: Incluir | J82: A | N82: =HYPERLINK("https://pubmed.ncbi.nlm.nih.gov/26820816/","abrir") -> abrir | O82: =IF(B82 < 2024, FALSE() , TRUE()) -> FALSE
A83: 26821376 | B83: 2016 | C83: Nakai Y | D83: Effectiveness of cardiac surgery in patients with trisomy 18: a single-institutional experience. | E83: BACKGROUND: Surgical repair for cardiac lesions has rarely been offered to patients with trisomy 18 because of their very short lifespans. We investigated the effectiveness of cardiac surgery in patients with trisomy 18. Patients and methods We performed a retrospective analysis of 20 consecutive patients with trisomy 18 and congenital cardiac anomalies who were evaluated between August, 2003 and July, 2013. All patients developed respiratory or cardiac failure due to excessive pulmonary blood flow. Patients were divided into two subgroups: one treated surgically (surgical group, n=10) and one treated without surgery (conservative group, n=10), primarily to compare the duration of survival between the groups. RESULTS: All the patients in the surgical group underwent cardiac surgery with pulmonary artery banding, including patent ductus arteriosus ligation in nine patients and coarctation repair in one. The duration of survival was significantly longer in the surgical group than in the conservative group (495.4±512.6 versus 93.1±76.2 days, respectively; p=0.03). A Cox proportional hazard model found cardiac surgery to be a significant predictor of survival time (risk ratio of 0.12, 95% confidence interval 0.016-0.63; p=0.01). CONCLUSIONS: Cardiac surgery was effective in prolonging survival by managing high pulmonary blood flow; however, the indication for surgery should be carefully considered on a case-by-case basis, because the risk of sudden death remains even after surgery. Patients' families should be provided with sufficient information to make decisions that will optimise the quality of life for both patients and their families. | F83: Cardiol Young | G83: Journal Article | H83: A | I83: Incluir | J83: A | N83: =HYPERLINK("https://pubmed.ncbi.nlm.nih.gov/26821376/","abrir") -> abrir | O83: =IF(B83 < 2024, FALSE() , TRUE()) -> FALSE
A84: 27167547 | B84: 2016 | C84: Goulart VV | D84: Intrauterine death in singleton pregnancies with trisomy 21, 18, 13 and monosomy X. | E84: A retrospective study from November 2004 to May 2012, conducted at the Obstetric Clinic of Hospital das Clínicas, Faculdade de Medicina, Universidade de São Paulo (HC-FMUSP), which included 92 singleton pregnancies with prenatal diagnosis of trisomy of chromosome 21 (T21), 18, 13 (T13/18) and monosomy X (45X), with diagnosis performed until the 26th week of pregnancy. The aim of the study was to describe the frequency and to investigate predictors of spontaneous fetal death (FD). Diagnosis (T21, n=36; T13/18, n=25; 45X, n=31) was made at a mean gestational age of 18.3±3.7 weeks, through chorionic villus biopsy (n=22,24%), amniocentesis (n=66, 72%) and cordocentesis (n=4, 4%). Major malformations were present in 45 (49%); with hydrops in 32 (35%) fetuses, more frequently in 45X [n=24/31, 77% vs. T21 (n=6/36, 17%) and T13/18 (n=2/25, 8%), p<0.001]. Specialized fetal echocardiography was performed in 60% (55/92). Of these, 60% (33/55) showed changes in heart morphology and/or function. Fetuses with T13/18 had a higher incidence of cardiac anomalies [60 vs. 25% (T21) and 29% (45X), p= 0.01]. FD occurred in 55 (60%) gestations, being more frequent in 45X [n=26/31, 84% vs. T21 (n=13/36, 36%) and T13/18 (n=16/25, 64%), p<0.01]. Stepwise analysis showed a correlation between hydrops and death in fetuses with T21 (LR= 4.29; 95CI=1.9-8.0, p<0.0001). In fetuses with 45X, the presence of echocardiographic abnormalities was associated with lower risk of FD (LR= 0.56; 95CI=0.27- 0.85, p=0.005). No predictive factors were identified in the T13/18 group. Intra- uterine lethality of aneuploid fetuses is high. Occurrence of hydrops increases risk of FD in pregnancies with T21. In pregnancies with 45X, the occurrence of echocardiographic changes reduces this risk. | F84: Rev Assoc Med Bras (1992) | G84: Journal Article | H84: B | I84: Incluir | J84: B | N84: =HYPERLINK("https://pubmed.ncbi.nlm.nih.gov/27167547/","abrir") -> abrir | O84: =IF(B84 < 2024, FALSE() , TRUE()) -> FALSE
A85: 27437608 | B85: 2016 | C85: Dotters-Katz SK | D85: Management of Pregnancy and Survival of Infants with Trisomy 13 or Trisomy 18. | E85: Objective The objective of this study was to describe antenatal/intrapartum management and survival of liveborn infants with known trisomy 13 (T13) or trisomy 18 (T18) based on planned neonatal care. Study Design This is a retrospective cohort study of singleton pregnancies complicated by T13/T18 at a tertiary center from 2004 to 2015. We included pregnancies with antenatal or neonatal cytogenetic T13/T18 diagnosis and excluded those which were terminated or had a fetal demise < 20 weeks. We compared antenatal/intrapartum management and neonatal survival by planned neonatal care, defined as either neonatal intervention (INT), including neonatal cardiopulmonary resuscitative measures or comfort care (CC) without resuscitative measures. Results In this study, 32 women (10 with T13 and 22 with T18) met study criteria; 12 (38%) elected INT and 20 (62%) CC. Compared with those who elected INT, women who elected CC were more likely to undergo elective induction (40 vs. 0%, p = 0.01), have an intrapartum stillbirth (0 vs. 32%, p = 0.14), and deliver vaginally (25 vs. 63%, p < 0.01). In neonatal survival analysis (n = 26), median survival was longer in the INT group compared with CC group (64 days [interquartile range, IQR: 2, 155) vs. 3 days [IQR]: 0.3, 42), p = 0.28), but survival to hospital discharge was similar (53 vs. 57%, p = 0.95). Conclusion Regardless of desired level of neonatal INT, many women who continue pregnancies complicated by T13/18 have infants who survive beyond hospital discharge. | F85: Am J Perinatol | G85: Journal Article | H85: A+B | I85: Incluir | J85: A+B | N85: =HYPERLINK("https://pubmed.ncbi.nlm.nih.gov/27437608/","abrir") -> abrir | O85: =IF(B85 < 2024, FALSE() , TRUE()) -> FALSE
A86: 27458947 | B86: 2016 | C86: Nelson KE | D86: Survival and Surgical Interventions for Children With Trisomy 13 and 18. | E86: IMPORTANCE: Trisomy 13 and 18 are genetic diagnoses with characteristic physical features, organ anomalies, and neurodevelopmental disability. Most children with these disorders die shortly after birth, although limited data suggest some children survive longer. Surgeries are controversial, and little evidence is available about outcomes. OBJECTIVE: To describe survival and utilization of any type of surgery among children with trisomy 13 and 18 born over a 21-year period in Ontario, Canada. DESIGN, SETTING, AND PARTICIPANTS: This retrospective cohort study used linked health administrative databases to identify children born in Ontario between April 1, 1991, and March 31, 2012, with a diagnosis code for trisomy 13 or 18 on a hospital record in the first year of life. Survival was calculated from birth and death dates; children living on March 31, 2013, were censored at their last clinical encounter. EXPOSURES: All procedures classified as occurring in an operating room through March 31, 2013, were categorized as major, intermediate, or minor surgeries. MAIN OUTCOMES AND MEASURES: Survival and surgical procedure utilization. RESULTS: The cohorts included 174 children with trisomy 13 (mean [SD] birth weight, 2.5 [0.7] kg; 98 [56.3%] female); and 254 children with trisomy 18 (mean birth weight, 1.8 [0.7] kg; 157 [61.8%] female), with follow-up times of 0 to more than 7000 days. Median (interquartile range [IQR]) survival times were 12.5 (2-195) days for trisomy 13 and 9 (2-92) days for trisomy 18. Mean 1-year survival for trisomy 13 was 19.8% (95% CI, 14.2%-26.1%) and 12.6% (95% CI, 8.9%-17.1%) for trisomy 18. Ten-year survival for trisomy 13 was 12.9% (95% CI, 8.4%-18.5%) and 9.8% (95% CI, 6.4%-14.0%) for trisomy 18. Survival did not change over the study period. Forty-one children (23.6%) with trisomy 13 and 35 children (13.8%) with trisomy 18 underwent surgeries, ranging from myringotomy to complex cardiac repair. Median age at first surgery for trisomy 13 was 92 (IQR, 30.5-384.5) days and for trisomy 18, it was 205.5 (IQR, 20.0-518.0) days. Kaplan-Meier curves showed 1-year survival after first surgery of 70.7% (95% CI, 54.3%-82.2%; n = 23) for trisomy 13 and 68.6% (95% CI, 50.5%-81.2%; n = 29) for trisomy 18. CONCLUSIONS AND RELEVANCE: Among children born with trisomy 13 or 18 in Ontario, early mortality was the most common outcome, but 10% to 13% survived for 10 years. Among children who underwent surgical interventions, 1-year survival was high. | F86: JAMA | G86: Journal Article; Research Support, Non-U.S. Gov't | H86: A | I86: Incluir | J86: A | N86: =HYPERLINK("https://pubmed.ncbi.nlm.nih.gov/27458947/","abrir") -> abrir | O86: =IF(B86 < 2024, FALSE() , TRUE()) -> FALSE
A87: 27530709 | B87: 2016 | C87: Donovan JH | D87: Medical interventions and survival by gender of children with trisomy 18. | E87: Research has typically shown limited aggressive medical interventions and low survival rates for children with full trisomy 18. Recent studies provide more positive results. This study examined 82 children with full trisomy 18 drawn from the Tracking Rare Incidence Syndromes (TRIS) project database. Children were classified into three groups according to the highest intervention received: "hospice or no intervention" (n = 5, 6.1%), "necessary interventions (enteral feeding, ventilator use)" (n = 46, 56.1%), and "aggressive interventions (surgery)" (n = 31, 37.8%). Seven of 14 male children (50%) and 52 of 68 female children (76.5%) were living at the time of survey completion. Additionally, information about any interventions used during the care of these children was also provided. It was found that three males (37.5%) and 28 females (48.3%) had used hospice care at some point; 12 males (85.7%) and 61 females (89.7%) received enteral feeding at some point; 7 males (58.3%) and 25 females (38.5%) had ventilator; and 7 males (50%) and 33 females (48.5%) underwent some form of surgery. These results suggest improved outcomes when given necessary and aggressive medical interventions. Implications and recommendations for further research are provided. © 2016 Wiley Periodicals, Inc. | F87: Am J Med Genet C Semin Med Genet | G87: Journal Article | H87: A | I87: Incluir | J87: A | N87: =HYPERLINK("https://pubmed.ncbi.nlm.nih.gov/27530709/","abrir") -> abrir | O87: =IF(B87 < 2024, FALSE() , TRUE()) -> FALSE
A88: 27550159 | B88: 2016 | C88: Janvier A | D88: Parental hopes, interventions, and survival of neonates with trisomy 13 and trisomy 18. | E88: Trisomy 13 and 18 are life-limiting conditions for which a palliative approach is frequently recommended. The objective of this study was to examine parental goals/decisions, the length of life of their child and factors associated with survival. Parents of children who lived with trisomy 13 or 18 that were part of English-speaking social networks were invited to participate in a questionnaire study. Participants answered questions about their hopes/goals, decisions regarding neonatal interventions, and the duration of their children's lives. The participants were 332 parents who answered questions about their 272 children (87% response rate based on site visits; 67% on invitations sent). When parents were asked about their hope after the diagnosis, the main themes invoked by parents were the following: meet their child alive (80% of parents with a prenatal diagnosis), spend some time as a family (72%), bring their child home (52%), and give their child a good life (66%). Parents wanted to give them a chance, but also reported their fears were medical complexity, pain and/or life in the hospital (61%). Healthcare providers recommended comfort care at birth to all parents. Life-sustaining interventions "as for any other child" was chosen as a plan of care by 25% of parents. Of the 216 children with full trisomy, 69% were discharged home after birth and 40% lived >1 y. The presence of a prenatal diagnosis was the strongest independent factor negatively associated with longevity: 36% of children with a prenatal diagnosis lived <24 hr and 47% were discharged home compared to 1% and 87%, respectively for children with a postnatal diagnosis (P < 0.01). Male gender, low-birth weight, and cardiac and/or cerebral anomaly were also associated with decreased survival (P < 0.05). After a prenatal diagnosis, palliative care at birth consisted of limited interventions, whereas after a postnatal diagnosis (median age of 6 days) it consisted of various interventions, including oxygen, ventilation, tube feeding and intravenous fluids, complicating the analysis. In conclusion, the goals of parents of children with trisomy 13 or 18 were to meet their child, be discharged home and be a family. Having a postnatal diagnosis was the independent factor most associated with these goals. Children with a postnatal diagnosis were treated "as any other children" until the diagnosis, which may give them a survival advantage, independent of palliative care. Rigorous transparency regarding specific interventions and outcomes may help personalize care for these children. © 2016 Wiley Periodicals, Inc. | F88: Am J Med Genet C Semin Med Genet | G88: Journal Article | H88: A | I88: Incluir | J88: A | N88: =HYPERLINK("https://pubmed.ncbi.nlm.nih.gov/27550159/","abrir") -> abrir | O88: =IF(B88 < 2024, FALSE() , TRUE()) -> FALSE
A89: 25388684 | B89: 2015 | C89: Denardin D | D89: Retrospective cohort of trisomy 18 (Edwards syndrome) in southern Brazil. | E89: CONTEXT AND OBJECTIVE: Trisomy 18 (T18), or Edwards syndrome, is a chromosomal disease characterized by a broad clinical picture and a poor prognosis. Our aim was to describe clinical, radiological and survival data of a cohort of patients prenatally diagnosed with T18. DESIGN AND SETTING: Retrospective single cohort in the Fetal Medicine Service of Hospital Materno Infantil Presidente Vargas (HMIPV). METHODS: All sequential patients with T18 registered at the Fetal Medicine Service of HMIPV between January 2005 and September 2013 were considered. We gathered their clinical, radiological and survival data and used the Kaplan-Meier test for survival analysis. RESULTS: Ten patients were diagnosed with T18, of whom seven (70%) were female. The majority (90%) were referred due to malformations seen on ultrasound. The mean gestational age at the first evaluation was 25.5 weeks. At karyotyping, the defects were considered multiple in only four patients (40%). All the fetuses presented full trisomy of chromosome 18. The main abnormality observed was congenital heart disease (n = 7). Intrauterine death occurred in half of the patients (50%). All live patients (n = 5) were born through cesarean section presenting low weight and low Apgar scores. The median length of survival after birth was 18 days. CONCLUSIONS: T18 is associated with a high risk of fetal and neonatal death. The majority of the patients present major malformations identified through ultrasound, such as congenital heart defects, which could help in identifying such cases prenatally. | F89: Sao Paulo Med J | G89: Journal Article | H89: A+B | I89: Incluir | J89: A+B | M89: Dados brasileiros. | N89: =HYPERLINK("https://pubmed.ncbi.nlm.nih.gov/25388684/","abrir") -> abrir | O89: =IF(B89 < 2024, FALSE() , TRUE()) -> FALSE
A90: 25612784 | B90: 2015 | C90: Costello JP | D90: A contemporary, single-institutional experience of surgical versus expectant management of congenital heart disease in trisomy 13 and 18 patients. | E90: The objective of this study was to examine a large institutional experience of patients with trisomy 13 and trisomy 18 in the setting of comorbid congenital heart disease and present the outcomes of surgical versus expectant management. It is a retrospective single-institution cohort study. Institutional review board approved this study. Thirteen consecutive trisomy 18 patients and three consecutive trisomy 13 patients (sixteen patients in total) with comorbid congenital heart disease who were evaluated by our institution's Division of Cardiovascular Surgery between January 2008 and December 2013 were included in the study. The primary outcome measures evaluated were operative mortality (for patients who received surgical management), overall mortality (for patients who received expectant management), and total length of survival during follow-up. Of the thirteen trisomy 18 patients, seven underwent surgical management and six received expectant management. With surgical management, operative mortality was 29 %, and 80 % of patients were alive after a median follow-up of 116 days. With expectant management, 50 % of patients died before hospital discharge. Of the three patients with trisomy 13, one patient underwent surgical management and two received expectant management. The patient who received surgical management with complete repair was alive at last follow-up over 2 years after surgery; both patients managed expectantly died before hospital discharge. Trisomy 13 and trisomy 18 patients with comorbid congenital heart disease can undergo successful cardiac surgical intervention. In this population, we advocate that nearly all patients with cardiovascular indications for operative congenital heart disease intervention should be offered complete surgical repair over palliative approaches for moderately complex congenital cardiac anomalies. | F90: Pediatr Cardiol | G90: Journal Article | H90: A | I90: Incluir | J90: A | N90: =HYPERLINK("https://pubmed.ncbi.nlm.nih.gov/25612784/","abrir") -> abrir | O90: =IF(B90 < 2024, FALSE() , TRUE()) -> FALSE
A91: 25847518 | B91: 2015 | C91: Ishitsuka K | D91: Medical procedures and outcomes of Japanese patients with trisomy 18 or trisomy 13: analysis of a nationwide administrative database of hospitalized patients. | E91: The choices of aggressive treatment for trisomy 18 (T18) and trisomy 13 (T13) remain controversial. Here, we describe the current medical procedures and outcomes of patients with T18 and T13 from a nationwide administrative database of hospitalized patients in Japan. We used the database to identify eligible patients with T18 (n = 438) and T13 (n = 133) who were first admitted to one of 200 hospitals between July 2010 and March 2013. Patients were divided into admission at day <7 (early neonatal) and admission at day ≥7 (late neonatal and post neonatal) groups, and we described the medical intervention and status at discharge for each group. In the day <7 groups, surgical interventions were performed for 56 (19.9%) T18 patients and 22 (34.4%) T13 patients, including pulmonary artery banding, and procedures for esophageal atresia and omphalocele. None received intracardiac surgery. The rate of patients discharged to home was higher in the day ≥7 groups than the day <7 groups (T18: 72.6 vs. 38.8%; T13: 73.9 vs. 21.9%, respectively). Our data show that a substantial number of patients with trisomy received surgery and were then discharged home, but, of these, a considerable number required home medical care. This included home oxygen therapy, home mechanical ventilation, and tube feeding. These findings will be useful to clinicians or families who care for patients with T18 and T13. | F91: Am J Med Genet A | G91: Journal Article; Research Support, Non-U.S. Gov't | H91: A | I91: Incluir | J91: A | N91: =HYPERLINK("https://pubmed.ncbi.nlm.nih.gov/25847518/","abrir") -> abrir | O91: =IF(B91 < 2024, FALSE() , TRUE()) -> FALSE
A92: 26307940 | B92: 2015 | C92: Imai K | D92: Differences in mortality and morbidity according to gestational ages and birth weights in infants with trisomy 18. | E92: The aim of this study was to clarify the effects of gestational age and birth weight on outcomes of the infants. Medical records of 36 infants with trisomy 18 admitted to Tokyo Women's Medical University Hospital from 1991 to 2012 were reviewed retrospectively. We compared clinical characteristics between term infants (n = 15) and preterm infants (n = 21). There were one very-low-birth-weight (VLBW) term infant (5%) and 12 VLBW preterm infants (80%). Although there were no significant differences in clinical characteristics and provided management between the two groups, none of the preterm infants achieved survival to discharge. On the other hand, 6 of 21 term infants (29%) achieved survival to discharge (P < 0.05). Similar results were obtained for comparisons between the VLBW infants and non-VLBW infants. Multiple logistic regression analysis revealed that shorter gestational age had a more negative impact than lower birth weight to survival to discharge in infants with trisomy 18. In both preterm and term groups, the infants who died before 30 days commonly died of respiratory failure or apnea. Whereas, the infants who survived more than 30 days mostly died of heart failure. | F92: Am J Med Genet A | G92: Journal Article | H92: A | I92: Incluir | J92: A | N92: =HYPERLINK("https://pubmed.ncbi.nlm.nih.gov/26307940/","abrir") -> abrir | O92: =IF(B92 < 2024, FALSE() , TRUE()) -> FALSE
A93: 24311518 | B93: 2014 | C93: Nishi E | D93: Surgical intervention for esophageal atresia in patients with trisomy 18. | E93: Trisomy 18 is a common chromosomal aberration syndrome involving growth impairment, various malformations, poor prognosis, and severe developmental delay in survivors. Although esophageal atresia (EA) with tracheoesophageal fistula (TEF) is a potentially fatal complication that can only be rescued through surgical correction, no reports have addressed the efficacy of surgical intervention for EA in patients with trisomy 18. We reviewed detailed clinical information of 24 patients with trisomy 18 and EA who were admitted to two neonatal intensive care units in Japan and underwent intensive treatment including surgical interventions from 1982 to 2009. Nine patients underwent only palliative surgery, including six who underwent only gastrostomy or both gastrostomy and jejunostomy (Group 1) and three who underwent gastrostomy and TEF division (Group 2). The other 15 patients underwent radical surgery, including 10 who underwent single-stage esophago-esophagostomy with TEF division (Group 3) and five who underwent two-stage operation (gastrostomy followed by esophago-esophagostomy with TEF division) (Group 4). No intraoperative death or anesthetic complications were noted. Enteral feeding was accomplished in 17 patients, three of whom were fed orally. Three patients could be discharged home. The 1-year survival rate was 17%: 27% in those receiving radical surgery (Groups 3 and 4); 0% in those receiving palliative surgery (Groups 1 and 2). Most causes of death were related to cardiac complications. EA is not an absolute poor prognostic factor in patients with trisomy 18 undergoing radical surgery for EA and intensive cardiac management. | F93: Am J Med Genet A | G93: Journal Article; Research Support, Non-U.S. Gov't | H93: A | I93: Incluir | J93: A | N93: =HYPERLINK("https://pubmed.ncbi.nlm.nih.gov/24311518/","abrir") -> abrir | O93: =IF(B93 < 2024, FALSE() , TRUE()) -> FALSE
A94: 24446439 | B94: 2014 | C94: Boghossian NS | D94: Mortality and morbidity of VLBW infants with trisomy 13 or trisomy 18. | E94: OBJECTIVE: Little is known about how very low birth weight (VLBW) affects survival and morbidities among infants with trisomy 13 (T13) or trisomy 18 (T18). We examined the care plans for VLBW infants with T13 or T18 and compared their risks of mortality and neonatal morbidities with VLBW infants with trisomy 21 and VLBW infants without birth defects. METHODS: Infants with birth weight 401 to 1500 g born or cared for at a participating center of the Eunice Kennedy Shriver National Institute of Child Health and Human Development Neonatal Research Network during the period 1994-2009 were studied. Poisson regression models were used to examine risk of death and neonatal morbidities among infants with T13 or T18. RESULTS: Of 52,262 VLBW infants, 38 (0.07%) had T13 and 128 (0.24%) had T18. Intensity of care in the delivery room varied depending on whether the trisomy was diagnosed before or after birth. The plan for subsequent care for the majority of the infants was to withdraw care or to provide comfort care. Eleven percent of infants with T13 and 9% of infants with T18 survived to hospital discharge. Survivors with T13 or T18 had significantly increased risk of patent ductus arteriosus and respiratory distress syndrome compared with infants without birth defects. No infant with T13 or T18 developed necrotizing enterocolitis. CONCLUSIONS: In this cohort of liveborn VLBW infants with T13 or T18, the timing of trisomy diagnosis affected the plan for care, survival was poor, and death usually occurred early. | F94: Pediatrics | G94: Comparative Study; Journal Article; Research Support, N.I.H., Extramural | H94: A | I94: Incluir | J94: A | N94: =HYPERLINK("https://pubmed.ncbi.nlm.nih.gov/24446439/","abrir") -> abrir | O94: =IF(B94 < 2024, FALSE() , TRUE()) -> FALSE
A95: 24993362 | B95: 2014 | C95: Springett AL | D95: Antenatal detection of Edwards (Trisomy 18) and Patau (Trisomy 13) syndrome: England and Wales 2005-2012. | E95: OBJECTIVES: Pregnancies with Edwards or Patau syndrome are often detected through screening for Down's syndrome. We aimed to evaluate the impact of screening for Down's syndrome on the prevalence of live births and antenatal diagnoses of Edwards and Patau syndrome. SETTING: England and Wales, 2005 to 2012. METHODS: Data from the National Down Syndrome Cytogenetic Register, which contains information on nearly all ante- or postnatally diagnosed cases of Edwards or Patau syndrome in which a karyotype was confirmed, were analysed. RESULTS: From 2005 to 2012, 3,941 diagnoses of Edwards syndrome and 1,567 diagnoses of Patau syndrome were recorded (prevalence of 7.0 and 2.8 per 10,000 births respectively). Only 11% (95% confidence interval [CI]: 10-12) of diagnoses of Edwards syndrome and 13% (95% CI: 11-14) of Patau syndrome were live births, resulting in live birth prevalences of 0.8 (95% CI: 0.7-0.8) and 0.4 (95% CI: 0.3-0.4) per 10,000 live births respectively. About 90% of pregnancies with Edwards or Patau syndrome were diagnosed antenatally, and this proportion remained constant over time. The proportion of diagnoses detected before 15 weeks increased from 50% in 2005 to 53% in 2012 for Edwards syndrome, and from 41% in 2005 to 63% in 2012 for Patau syndrome. CONCLUSIONS: Almost 700 women per year had a pregnancy with Edwards or Patau syndrome. Over 90% of these pregnancies were detected antenatally, with the increased use of first trimester screening for Down's syndrome resulting in the reduction in the mean gestational age at diagnosis of these syndromes. | F95: J Med Screen | G95: Journal Article; Research Support, Non-U.S. Gov't | H95: B | I95: Incluir | J95: B | M95: Verificar no texto completo se há dado específico e separável da T18 | N95: =HYPERLINK("https://pubmed.ncbi.nlm.nih.gov/24993362/","abrir") -> abrir | O95: =IF(B95 < 2024, FALSE() , TRUE()) -> FALSE
A96: 22562870 | B96: 2013 | C96: Burke AL | D96: Natural history of fetal trisomy 18 after prenatal diagnosis. | E96: OBJECTIVE: To evaluate the natural fetal and neonatal outcome for pregnancies with an established prenatal diagnosis of fetal trisomy 18, and a parental decision for continuation of the pregnancy. METHODS: The obstetric and neonatal outcome data for 23 such pregnancies, diagnosed at a single referral Fetal Medicine Centre, were retrospectively obtained. RESULTS: The overall intrauterine fetal death rate was 61%, with a progressive decline in live fetuses up to 39 weeks gestation. For fetuses diagnosed before 20 weeks gestation, there was a trend towards a higher intrauterine fetal death rate (88%), in comparison to those diagnosed after this period (44%) (p=0.06). For live births, the preterm delivery rate was 44%. All infants born alive died within 48 h of birth. CONCLUSION: These data provide reliable information for parental counselling pertaining to risk of intrauterine death when trisomy 18 is diagnosed prenatally. These findings suggest that long-term survival implications for trisomy 18 are different when it is diagnosed prenatally. | F96: Arch Dis Child Fetal Neonatal Ed | G96: Journal Article | H96: A+B | I96: Incluir | J96: B | N96: =HYPERLINK("https://pubmed.ncbi.nlm.nih.gov/22562870/","abrir") -> abrir | O96: =IF(B96 < 2024, FALSE() , TRUE()) -> FALSE
